{
    "Objects": [
        {
            "name": "Land_Underground_Entrance",
            "pos": [
                7073.2109375,
                290.5457458496094,
                4686.24560546875
            ],
            "ypr": [
                -127.435302734375,
                0.0,
                0.0
            ],
            "scale": 0.9977172613143921,
            "enableCEPersistency": 0
        },
        {
            "name": "Land_Underground_Stairs_Start",
            "pos": [
                6938.8212890625,
                285.7254638671875,
                4626.9267578125
            ],
            "ypr": [
                -90.00006866455078,
                0.0,
                -0.0
            ],
            "scale": 0.9999995231628418,
            "enableCEPersistency": 0
        },
        {
            "name": "Land_Underground_Stairs_Block",
            "pos": [
                6938.83251953125,
                290.25,
                4626.91748046875
            ],
            "ypr": [
                -90.00009155273438,
                0.0,
                0.0
            ],
            "scale": 0.9999988079071045,
            "enableCEPersistency": 0
        },
        {
            "name": "Land_Underground_Stairs_Block",
            "pos": [
                6938.830078125,
                295.25,
                4626.919921875
            ],
            "ypr": [
                -90.00009155273438,
                0.0,
                0.0
            ],
            "scale": 0.9999979734420776,
            "enableCEPersistency": 0
        },
        {
            "name": "Land_Underground_Stairs_Block_Corridor",
            "pos": [
                6938.7900390625,
                300.25,
                4626.93017578125
            ],
            "ypr": [
                -90.0,
                0.0,
                0.0
            ],
            "scale": 0.9999988079071045,
            "enableCEPersistency": 0
        },
        {
            "name": "Land_Underground_Stairs_Block",
            "pos": [
                6938.83251953125,
                305.25,
                4626.91748046875
            ],
            "ypr": [
                -90.00009155273438,
                0.0,
                0.0
            ],
            "scale": 0.9999984502792358,
            "enableCEPersistency": 0
        },
        {
            "name": "Land_Underground_Stairs_Block",
            "pos": [
                6938.830078125,
                310.25,
                4626.919921875
            ],
            "ypr": [
                -90.00009155273438,
                0.0,
                0.0
            ],
            "scale": 0.9999976754188538,
            "enableCEPersistency": 0
        },
        {
            "name": "Land_Underground_Stairs_Block_Corridor",
            "pos": [
                6938.7900390625,
                315.25,
                4626.93017578125
            ],
            "ypr": [
                -90.0,
                0.0,
                0.0
            ],
            "scale": 0.9999984502792358,
            "enableCEPersistency": 0
        },
        {
            "name": "Land_Underground_Stairs_Block",
            "pos": [
                6938.830078125,
                320.25,
                4626.919921875
            ],
            "ypr": [
                -90.00009155273438,
                0.0,
                0.0
            ],
            "scale": 0.9999966621398926,
            "enableCEPersistency": 0
        },
        {
            "name": "Land_Underground_Stairs_Exit",
            "pos": [
                6938.81005859375,
                330.1499938964844,
                4628.419921875
            ],
            "ypr": [
                -90.56629180908203,
                0.0,
                0.0
            ],
            "scale": 0.9999886751174927,
            "enableCEPersistency": 0
        },
        {
            "name": "Land_Underground_Floor_Crew",
            "pos": [
                6951.240234375,
                300.6000061035156,
                4615.2900390625
            ],
            "ypr": [
                90.0,
                0.0,
                0.0
            ],
            "scale": 0.9999988079071045,
            "enableCEPersistency": 0
        },
        {
            "name": "Land_Underground_Stairs_Collapsed",
            "pos": [
                6941.97705078125,
                300.25,
                4604.18408203125
            ],
            "ypr": [
                -90.38370513916016,
                0.0,
                0.0
            ],
            "scale": 0.9999920129776001,
            "enableCEPersistency": 0
        },
        {
            "name": "Land_Underground_Floor_Comms",
            "pos": [
                6962.98583984375,
                300.6000061035156,
                4592.52294921875
            ],
            "ypr": [
                90.32999420166016,
                0.0,
                0.0
            ],
            "scale": 0.9999887347221375,
            "enableCEPersistency": 0
        },
        {
            "name": "Land_Underground_Storage_Big",
            "pos": [
                6970.36181640625,
                300.6499938964844,
                4612.7880859375
            ],
            "ypr": [
                -89.9999008178711,
                0.0,
                0.0
            ],
            "scale": 0.9999990463256836,
            "enableCEPersistency": 0
        },
        {
            "name": "Land_Underground_Storage_Big",
            "pos": [
                6995.39013671875,
                300.6499938964844,
                4612.943359375
            ],
            "ypr": [
                90.05189514160156,
                0.0,
                0.0
            ],
            "scale": 0.9999943375587463,
            "enableCEPersistency": 0
        },
        {
            "name": "Land_Underground_Storage_Barracks",
            "pos": [
                6995.33984375,
                300.6499938964844,
                4599.2236328125
            ],
            "ypr": [
                90.0,
                0.0,
                0.0
            ],
            "scale": 0.9999990463256836,
            "enableCEPersistency": 0
        },
        {
            "name": "Land_Underground_Storage_Ammo",
            "pos": [
                6995.35986328125,
                300.6499938964844,
                4585.52978515625
            ],
            "ypr": [
                90.0,
                0.0,
                0.0
            ],
            "scale": 0.9999980926513672,
            "enableCEPersistency": 0
        },
        {
            "name": "Land_Wall_Gate_Fen4",
            "pos": [
                6970.8603515625,
                300.6499938964844,
                4581.625
            ],
            "ypr": [
                179.99989318847657,
                89.73311614990235,
                179.99989318847657
            ],
            "scale": 0.9999986290931702,
            "enableCEPersistency": 0
        },
        {
            "name": "Land_Wall_Gate_Fen4",
            "pos": [
                6974.8642578125,
                300.6499938964844,
                4581.625
            ],
            "ypr": [
                179.99989318847657,
                89.71675872802735,
                179.99989318847657
            ],
            "scale": 0.9999985694885254,
            "enableCEPersistency": 0
        },
        {
            "name": "Land_Wall_Gate_Fen4",
            "pos": [
                6978.8681640625,
                300.6499938964844,
                4581.625
            ],
            "ypr": [
                179.99989318847657,
                89.69998168945313,
                179.99989318847657
            ],
            "scale": 0.9999985098838806,
            "enableCEPersistency": 0
        },
        {
            "name": "Land_Wall_Gate_Fen4",
            "pos": [
                6982.8720703125,
                300.6499938964844,
                4581.625
            ],
            "ypr": [
                179.99989318847657,
                89.68347930908203,
                179.99989318847657
            ],
            "scale": 0.9999984502792358,
            "enableCEPersistency": 0
        },
        {
            "name": "Land_Wall_Gate_Fen4",
            "pos": [
                6982.8720703125,
                300.6499938964844,
                4583.4267578125
            ],
            "ypr": [
                179.99989318847657,
                89.66720581054688,
                179.99989318847657
            ],
            "scale": 0.9999983906745911,
            "enableCEPersistency": 0
        },
        {
            "name": "Land_Wall_Gate_Fen4",
            "pos": [
                6982.8720703125,
                300.6499938964844,
                4585.12841796875
            ],
            "ypr": [
                179.99989318847657,
                89.66720581054688,
                179.99989318847657
            ],
            "scale": 0.9999983906745911,
            "enableCEPersistency": 0
        },
        {
            "name": "Land_Wall_Gate_Fen4",
            "pos": [
                6982.8720703125,
                300.6499938964844,
                4586.93017578125
            ],
            "ypr": [
                179.99989318847657,
                89.65113067626953,
                179.99989318847657
            ],
            "scale": 0.9999983310699463,
            "enableCEPersistency": 0
        },
        {
            "name": "Land_Wall_Gate_Fen4",
            "pos": [
                6982.8720703125,
                300.6499938964844,
                4588.73193359375
            ],
            "ypr": [
                179.99989318847657,
                89.65113067626953,
                179.99989318847657
            ],
            "scale": 0.9999983310699463,
            "enableCEPersistency": 0
        },
        {
            "name": "Land_Wall_Gate_Fen4",
            "pos": [
                6982.8720703125,
                300.6499938964844,
                4590.53369140625
            ],
            "ypr": [
                179.99989318847657,
                89.61896514892578,
                179.99989318847657
            ],
            "scale": 0.999998152256012,
            "enableCEPersistency": 0
        },
        {
            "name": "Land_Wall_Gate_Fen4",
            "pos": [
                6982.8720703125,
                300.6499938964844,
                4592.2353515625
            ],
            "ypr": [
                179.99989318847657,
                89.66720581054688,
                179.99989318847657
            ],
            "scale": 0.9999983906745911,
            "enableCEPersistency": 0
        },
        {
            "name": "Land_Wall_Gate_Fen4",
            "pos": [
                6982.8720703125,
                300.6499938964844,
                4595.73876953125
            ],
            "ypr": [
                179.99989318847657,
                89.65113067626953,
                179.99989318847657
            ],
            "scale": 0.9999983310699463,
            "enableCEPersistency": 0
        },
        {
            "name": "Land_Wall_Gate_Fen4",
            "pos": [
                6982.8720703125,
                300.6499938964844,
                4597.54052734375
            ],
            "ypr": [
                179.99989318847657,
                89.63522338867188,
                179.99989318847657
            ],
            "scale": 0.9999982118606567,
            "enableCEPersistency": 0
        },
        {
            "name": "Land_Wall_Gate_Fen4",
            "pos": [
                6982.8720703125,
                300.6499938964844,
                4599.34228515625
            ],
            "ypr": [
                179.99989318847657,
                89.63522338867188,
                179.99989318847657
            ],
            "scale": 0.9999982118606567,
            "enableCEPersistency": 0
        },
        {
            "name": "Land_Wall_Gate_Fen4",
            "pos": [
                6982.8720703125,
                300.6499938964844,
                4601.14404296875
            ],
            "ypr": [
                179.99989318847657,
                89.61896514892578,
                179.99989318847657
            ],
            "scale": 0.999998152256012,
            "enableCEPersistency": 0
        },
        {
            "name": "Land_Wall_Gate_Fen4",
            "pos": [
                6982.8720703125,
                300.6499938964844,
                4604.6474609375
            ],
            "ypr": [
                179.99989318847657,
                89.63522338867188,
                179.99989318847657
            ],
            "scale": 0.9999982118606567,
            "enableCEPersistency": 0
        },
        {
            "name": "Land_Wall_Gate_Fen4",
            "pos": [
                6982.8720703125,
                300.6499938964844,
                4606.34912109375
            ],
            "ypr": [
                -179.42715454101563,
                88.34458923339844,
                179.99989318847657
            ],
            "scale": 0.9999917149543762,
            "enableCEPersistency": 0
        },
        {
            "name": "Land_Wall_Gate_Fen4",
            "pos": [
                6982.8720703125,
                300.6499938964844,
                4608.15087890625
            ],
            "ypr": [
                179.99989318847657,
                89.61896514892578,
                179.99989318847657
            ],
            "scale": 0.999998152256012,
            "enableCEPersistency": 0
        },
        {
            "name": "Land_Wall_Gate_Fen4",
            "pos": [
                6982.8720703125,
                300.6499938964844,
                4609.95263671875
            ],
            "ypr": [
                179.99989318847657,
                89.61896514892578,
                179.99989318847657
            ],
            "scale": 0.999998152256012,
            "enableCEPersistency": 0
        },
        {
            "name": "Land_Wall_Gate_Fen4",
            "pos": [
                6982.8720703125,
                300.6499938964844,
                4611.75439453125
            ],
            "ypr": [
                179.99989318847657,
                89.60336303710938,
                179.99989318847657
            ],
            "scale": 0.9999980926513672,
            "enableCEPersistency": 0
        },
        {
            "name": "Land_Wall_Gate_Fen4",
            "pos": [
                6982.8720703125,
                300.6499938964844,
                4602.845703125
            ],
            "ypr": [
                179.99989318847657,
                89.65113067626953,
                179.99989318847657
            ],
            "scale": 0.9999983310699463,
            "enableCEPersistency": 0
        },
        {
            "name": "Land_Wall_Gate_Fen4",
            "pos": [
                6982.8720703125,
                300.6499938964844,
                4615.35791015625
            ],
            "ypr": [
                179.99989318847657,
                89.61896514892578,
                179.99989318847657
            ],
            "scale": 0.999998152256012,
            "enableCEPersistency": 0
        },
        {
            "name": "Land_Wall_Gate_Fen4",
            "pos": [
                6982.8701171875,
                300.6499938964844,
                4617.06005859375
            ],
            "ypr": [
                -179.99990844726563,
                89.60385131835938,
                -179.99990844726563
            ],
            "scale": 0.9999980926513672,
            "enableCEPersistency": 0
        },
        {
            "name": "Land_Wall_Gate_Fen4",
            "pos": [
                6982.8720703125,
                300.6499938964844,
                4613.55615234375
            ],
            "ypr": [
                179.99989318847657,
                89.63522338867188,
                179.99989318847657
            ],
            "scale": 0.9999982118606567,
            "enableCEPersistency": 0
        },
        {
            "name": "StaticObj_BusStation_wall",
            "pos": [
                6970.71044921875,
                302.20001220703127,
                4582.3408203125
            ],
            "ypr": [
                89.524658203125,
                0.0,
                0.0
            ],
            "scale": 0.999995231628418,
            "enableCEPersistency": 0
        },
        {
            "name": "StaticObj_BusStation_wall",
            "pos": [
                6970.71044921875,
                302.20001220703127,
                4580.138671875
            ],
            "ypr": [
                89.524658203125,
                0.0,
                0.0
            ],
            "scale": 0.9999951720237732,
            "enableCEPersistency": 0
        },
        {
            "name": "StaticObj_BusStation_wall",
            "pos": [
                6973.71337890625,
                302.20001220703127,
                4582.3603515625
            ],
            "ypr": [
                89.524658203125,
                0.0,
                0.0
            ],
            "scale": 0.9999951720237732,
            "enableCEPersistency": 0
        },
        {
            "name": "StaticObj_BusStation_wall",
            "pos": [
                6973.71337890625,
                302.20001220703127,
                4580.158203125
            ],
            "ypr": [
                89.524658203125,
                0.0,
                0.0
            ],
            "scale": 0.9999951124191284,
            "enableCEPersistency": 0
        },
        {
            "name": "StaticObj_BusStation_wall",
            "pos": [
                6976.42578125,
                302.20001220703127,
                4582.38720703125
            ],
            "ypr": [
                89.524658203125,
                0.0,
                0.0
            ],
            "scale": 0.9999949932098389,
            "enableCEPersistency": 0
        },
        {
            "name": "StaticObj_BusStation_wall",
            "pos": [
                6976.42578125,
                302.20001220703127,
                4580.18505859375
            ],
            "ypr": [
                89.524658203125,
                0.0,
                0.0
            ],
            "scale": 0.9999948740005493,
            "enableCEPersistency": 0
        },
        {
            "name": "StaticObj_BusStation_wall",
            "pos": [
                6979.4287109375,
                302.20001220703127,
                4582.40673828125
            ],
            "ypr": [
                89.524658203125,
                0.0,
                0.0
            ],
            "scale": 0.9999948740005493,
            "enableCEPersistency": 0
        },
        {
            "name": "StaticObj_BusStation_wall",
            "pos": [
                6979.4287109375,
                302.20001220703127,
                4580.20458984375
            ],
            "ypr": [
                89.524658203125,
                0.0,
                0.0
            ],
            "scale": 0.9999948740005493,
            "enableCEPersistency": 0
        },
        {
            "name": "StaticObj_BusStation_wall",
            "pos": [
                6982.431640625,
                302.20001220703127,
                4580.20458984375
            ],
            "ypr": [
                89.524658203125,
                0.0,
                0.0
            ],
            "scale": 0.9999948143959045,
            "enableCEPersistency": 0
        },
        {
            "name": "StaticObj_BusStation_wall",
            "pos": [
                6983.4326171875,
                302.20001220703127,
                4580.20458984375
            ],
            "ypr": [
                89.524658203125,
                0.0,
                0.0
            ],
            "scale": 0.9999947547912598,
            "enableCEPersistency": 0
        },
        {
            "name": "StaticObj_BusStation_wall",
            "pos": [
                6980.72998046875,
                302.20001220703127,
                4584.00830078125
            ],
            "ypr": [
                0.28645655512809756,
                0.0,
                0.0
            ],
            "scale": 0.9999854564666748,
            "enableCEPersistency": 0
        },
        {
            "name": "StaticObj_BusStation_wall",
            "pos": [
                6980.72998046875,
                302.20001220703127,
                4586.9111328125
            ],
            "ypr": [
                0.28645652532577517,
                0.0,
                0.0
            ],
            "scale": 0.99998539686203,
            "enableCEPersistency": 0
        },
        {
            "name": "StaticObj_BusStation_wall",
            "pos": [
                6980.72998046875,
                302.20001220703127,
                4589.9140625
            ],
            "ypr": [
                0.28645652532577517,
                0.0,
                0.0
            ],
            "scale": 0.9999853372573853,
            "enableCEPersistency": 0
        },
        {
            "name": "StaticObj_BusStation_wall",
            "pos": [
                6980.72998046875,
                302.20001220703127,
                4592.81689453125
            ],
            "ypr": [
                0.28645649552345278,
                0.0,
                0.0
            ],
            "scale": 0.9999852776527405,
            "enableCEPersistency": 0
        },
        {
            "name": "StaticObj_BusStation_wall",
            "pos": [
                6980.72509765625,
                302.20001220703127,
                4595.8271484375
            ],
            "ypr": [
                0.28645646572113039,
                0.0,
                0.0
            ],
            "scale": 0.9999852180480957,
            "enableCEPersistency": 0
        },
        {
            "name": "StaticObj_BusStation_wall",
            "pos": [
                6980.72509765625,
                302.20001220703127,
                4598.72998046875
            ],
            "ypr": [
                0.286456435918808,
                0.0,
                0.0
            ],
            "scale": 0.9999851584434509,
            "enableCEPersistency": 0
        },
        {
            "name": "StaticObj_BusStation_wall",
            "pos": [
                6980.72509765625,
                302.20001220703127,
                4601.6328125
            ],
            "ypr": [
                0.2864563763141632,
                0.0,
                0.0
            ],
            "scale": 0.9999850988388062,
            "enableCEPersistency": 0
        },
        {
            "name": "StaticObj_BusStation_wall",
            "pos": [
                6980.72509765625,
                302.20001220703127,
                4604.435546875
            ],
            "ypr": [
                0.28645631670951846,
                0.0,
                0.0
            ],
            "scale": 0.9999850392341614,
            "enableCEPersistency": 0
        },
        {
            "name": "StaticObj_Wall_FenG_Pole",
            "pos": [
                7002.52001953125,
                286.3999938964844,
                4613.740234375
            ],
            "ypr": [
                0.0,
                0.0,
                0.0
            ],
            "scale": 9.999992370605469,
            "enableCEPersistency": 0
        },
        {
            "name": "StaticObj_Wall_FenG_Pole",
            "pos": [
                6988.30615234375,
                286.3999938964844,
                4613.740234375
            ],
            "ypr": [
                0.0,
                0.0,
                0.0
            ],
            "scale": 9.999992370605469,
            "enableCEPersistency": 0
        },
        {
            "name": "StaticObj_Wall_FenG_Pole",
            "pos": [
                6977.1953125,
                286.3999938964844,
                4613.740234375
            ],
            "ypr": [
                0.0,
                0.0,
                0.0
            ],
            "scale": 9.999992370605469,
            "enableCEPersistency": 0
        },
        {
            "name": "StaticObj_Wall_FenG_Pole",
            "pos": [
                6962.1806640625,
                286.3999938964844,
                4613.740234375
            ],
            "ypr": [
                0.0,
                0.0,
                0.0
            ],
            "scale": 9.999992370605469,
            "enableCEPersistency": 0
        },
        {
            "name": "StaticObj_Wall_FenG_Pole",
            "pos": [
                7002.52001953125,
                286.3999938964844,
                4598.3251953125
            ],
            "ypr": [
                0.0,
                0.0,
                0.0
            ],
            "scale": 9.999992370605469,
            "enableCEPersistency": 0
        },
        {
            "name": "StaticObj_Wall_FenG_Pole",
            "pos": [
                6988.30615234375,
                286.3999938964844,
                4598.3251953125
            ],
            "ypr": [
                0.0,
                0.0,
                0.0
            ],
            "scale": 9.999992370605469,
            "enableCEPersistency": 0
        },
        {
            "name": "StaticObj_Wall_FenG_Pole",
            "pos": [
                6962.1806640625,
                286.3999938964844,
                4598.3251953125
            ],
            "ypr": [
                0.0,
                0.0,
                0.0
            ],
            "scale": 9.999992370605469,
            "enableCEPersistency": 0
        },
        {
            "name": "StaticObj_Wall_FenG_Pole",
            "pos": [
                7002.52001953125,
                286.3999938964844,
                4581.9091796875
            ],
            "ypr": [
                0.0,
                0.0,
                0.0
            ],
            "scale": 9.999992370605469,
            "enableCEPersistency": 0
        },
        {
            "name": "StaticObj_Wall_FenG_Pole",
            "pos": [
                6988.30615234375,
                286.3999938964844,
                4581.9091796875
            ],
            "ypr": [
                0.0,
                0.0,
                0.0
            ],
            "scale": 9.999992370605469,
            "enableCEPersistency": 0
        },
        {
            "name": "StaticObj_Wall_FenG_Pole",
            "pos": [
                6962.1806640625,
                286.3999938964844,
                4581.9091796875
            ],
            "ypr": [
                0.0,
                0.0,
                0.0
            ],
            "scale": 9.999992370605469,
            "enableCEPersistency": 0
        },
        {
            "name": "Land_Underground_Corridor_Main_Both",
            "pos": [
                6952.06005859375,
                315.6000061035156,
                4617.6201171875
            ],
            "ypr": [
                179.99990844726563,
                0.0,
                0.0
            ],
            "scale": 0.9999947547912598,
            "enableCEPersistency": 0
        },
        {
            "name": "Land_Underground_Corridor_Connector_Inv",
            "pos": [
                6952.2099609375,
                315.6000061035156,
                4601.4501953125
            ],
            "ypr": [
                -90.0,
                0.0,
                0.0
            ],
            "scale": 0.9999933242797852,
            "enableCEPersistency": 0
        },
        {
            "name": "Land_Underground_Tunnel_Single_Right",
            "pos": [
                6962.22802734375,
                315.6000061035156,
                4587.8828125
            ],
            "ypr": [
                -90.0,
                0.0,
                0.0
            ],
            "scale": 0.9999969005584717,
            "enableCEPersistency": 0
        },
        {
            "name": "Land_Underground_Tunnel_Single",
            "pos": [
                6967.09130859375,
                315.6000061035156,
                4587.88671875
            ],
            "ypr": [
                -90.0,
                0.0,
                0.0
            ],
            "scale": 0.9999969005584717,
            "enableCEPersistency": 0
        },
        {
            "name": "Land_Underground_Tunnel_Single_Right",
            "pos": [
                6948.693359375,
                315.6000061035156,
                4594.6787109375
            ],
            "ypr": [
                -179.99990844726563,
                0.0,
                0.0
            ],
            "scale": 0.9999949932098389,
            "enableCEPersistency": 0
        },
        {
            "name": "Land_Underground_Storage_Laboratory",
            "pos": [
                6931.5,
                315.6000061035156,
                4587.27001953125
            ],
            "ypr": [
                -91.67318725585938,
                0.0,
                0.0
            ],
            "scale": 0.9999977946281433,
            "enableCEPersistency": 0
        },
        {
            "name": "Land_Underground_Storage_Prison",
            "pos": [
                6969.21533203125,
                315.6000061035156,
                4616.13330078125
            ],
            "ypr": [
                90.0,
                0.0,
                0.0
            ],
            "scale": 0.9999972581863403,
            "enableCEPersistency": 0
        },
        {
            "name": "Land_Underground_Stairs_Block_Corridor",
            "pos": [
                6942.625,
                315.6000061035156,
                4619.56787109375
            ],
            "ypr": [
                0.0,
                0.0,
                0.0
            ],
            "scale": 0.9999990463256836,
            "enableCEPersistency": 0
        },
        {
            "name": "Land_Underground_Storage_Big_Vent",
            "pos": [
                6982.5234375,
                315.6000061035156,
                4587.91650390625
            ],
            "ypr": [
                90.0,
                0.0,
                0.0
            ],
            "scale": 0.9999971389770508,
            "enableCEPersistency": 0
        },
        {
            "name": "Land_Underground_Storage_Workshop",
            "pos": [
                6975.17236328125,
                300.6499938964844,
                4630.73095703125
            ],
            "ypr": [
                90.0,
                0.0,
                0.0
            ],
            "scale": 0.9999959468841553,
            "enableCEPersistency": 0
        },
        {
            "name": "Land_Wall_Gate_Fen4",
            "pos": [
                6982.8720703125,
                300.6499938964844,
                4618.060546875
            ],
            "ypr": [
                179.99989318847657,
                89.58740234375,
                179.99989318847657
            ],
            "scale": 0.9999980330467224,
            "enableCEPersistency": 0
        },
        {
            "name": "Land_Wall_Gate_Fen4",
            "pos": [
                6982.8720703125,
                300.6499938964844,
                4609.15185546875
            ],
            "ypr": [
                179.99989318847657,
                89.63522338867188,
                179.99989318847657
            ],
            "scale": 0.9999982118606567,
            "enableCEPersistency": 0
        },
        {
            "name": "Land_Wall_Gate_Fen4",
            "pos": [
                6982.8720703125,
                300.6499938964844,
                4621.6640625
            ],
            "ypr": [
                179.99989318847657,
                89.60336303710938,
                179.99989318847657
            ],
            "scale": 0.9999980926513672,
            "enableCEPersistency": 0
        },
        {
            "name": "Land_Wall_Gate_Fen4",
            "pos": [
                6982.8701171875,
                300.6499938964844,
                4623.3662109375
            ],
            "ypr": [
                -179.99989318847657,
                89.58930206298828,
                -179.99989318847657
            ],
            "scale": 0.9999980926513672,
            "enableCEPersistency": 0
        },
        {
            "name": "Land_Wall_Gate_Fen4",
            "pos": [
                6982.8720703125,
                300.6499938964844,
                4619.8623046875
            ],
            "ypr": [
                179.99989318847657,
                89.61896514892578,
                179.99989318847657
            ],
            "scale": 0.999998152256012,
            "enableCEPersistency": 0
        },
        {
            "name": "Land_Wall_Gate_Fen4",
            "pos": [
                6978.96826171875,
                300.6499938964844,
                4621.6640625
            ],
            "ypr": [
                179.99989318847657,
                89.58740234375,
                179.99989318847657
            ],
            "scale": 0.9999980330467224,
            "enableCEPersistency": 0
        },
        {
            "name": "Land_Wall_Gate_Fen4",
            "pos": [
                6978.96630859375,
                300.6499938964844,
                4623.3662109375
            ],
            "ypr": [
                -179.99989318847657,
                89.57386779785156,
                -179.99989318847657
            ],
            "scale": 0.9999979734420776,
            "enableCEPersistency": 0
        },
        {
            "name": "Land_Wall_Gate_Fen4",
            "pos": [
                6974.96435546875,
                300.6499938964844,
                4621.6640625
            ],
            "ypr": [
                179.99989318847657,
                89.57157897949219,
                179.99989318847657
            ],
            "scale": 0.9999979734420776,
            "enableCEPersistency": 0
        },
        {
            "name": "Land_Wall_Gate_Fen4",
            "pos": [
                6974.96240234375,
                300.6499938964844,
                4623.3662109375
            ],
            "ypr": [
                -179.99989318847657,
                89.55809020996094,
                -179.99989318847657
            ],
            "scale": 0.9999979138374329,
            "enableCEPersistency": 0
        },
        {
            "name": "Land_Wall_Gate_Fen4",
            "pos": [
                6971.060546875,
                300.6499938964844,
                4621.6640625
            ],
            "ypr": [
                179.99989318847657,
                89.55587768554688,
                179.99989318847657
            ],
            "scale": 0.9999979138374329,
            "enableCEPersistency": 0
        },
        {
            "name": "Land_Wall_Gate_Fen4",
            "pos": [
                6971.05859375,
                300.6499938964844,
                4623.3662109375
            ],
            "ypr": [
                -179.99989318847657,
                89.54241943359375,
                -179.99989318847657
            ],
            "scale": 0.9999978542327881,
            "enableCEPersistency": 0
        },
        {
            "name": "Land_Wall_Gate_Fen4",
            "pos": [
                6967.056640625,
                300.6499938964844,
                4621.6640625
            ],
            "ypr": [
                179.99989318847657,
                89.54029083251953,
                179.99989318847657
            ],
            "scale": 0.9999978542327881,
            "enableCEPersistency": 0
        },
        {
            "name": "Land_Wall_Gate_Fen4",
            "pos": [
                6967.0546875,
                300.6499938964844,
                4623.3662109375
            ],
            "ypr": [
                -179.99989318847657,
                89.52729034423828,
                -179.99989318847657
            ],
            "scale": 0.9999978542327881,
            "enableCEPersistency": 0
        },
        {
            "name": "Land_Wall_Gate_Fen4",
            "pos": [
                6963.052734375,
                300.6499938964844,
                4621.6640625
            ],
            "ypr": [
                179.99989318847657,
                89.5248031616211,
                179.99989318847657
            ],
            "scale": 0.9999977946281433,
            "enableCEPersistency": 0
        },
        {
            "name": "Land_Wall_Gate_Fen4",
            "pos": [
                6963.05078125,
                300.6499938964844,
                4623.3662109375
            ],
            "ypr": [
                -179.99989318847657,
                89.51261138916016,
                -179.99989318847657
            ],
            "scale": 0.9999978542327881,
            "enableCEPersistency": 0
        },
        {
            "name": "Land_Wall_Gate_Fen4",
            "pos": [
                6963.052734375,
                300.6499938964844,
                4625.0673828125
            ],
            "ypr": [
                179.99989318847657,
                89.50940704345703,
                179.99989318847657
            ],
            "scale": 0.9999977350234985,
            "enableCEPersistency": 0
        },
        {
            "name": "Land_Wall_Gate_Fen4",
            "pos": [
                6963.05078125,
                300.6499938964844,
                4626.76953125
            ],
            "ypr": [
                -179.99989318847657,
                89.49836730957031,
                -179.99989318847657
            ],
            "scale": 0.9999978542327881,
            "enableCEPersistency": 0
        },
        {
            "name": "Land_Wall_Gate_Fen4",
            "pos": [
                6963.052734375,
                300.6499938964844,
                4628.470703125
            ],
            "ypr": [
                179.99989318847657,
                89.49409484863281,
                179.99989318847657
            ],
            "scale": 0.9999976754188538,
            "enableCEPersistency": 0
        },
        {
            "name": "Land_Wall_Gate_Fen4",
            "pos": [
                6963.05078125,
                300.6499938964844,
                4630.1728515625
            ],
            "ypr": [
                -179.99989318847657,
                89.484130859375,
                -179.99989318847657
            ],
            "scale": 0.9999977350234985,
            "enableCEPersistency": 0
        },
        {
            "name": "Land_Wall_Gate_Fen4",
            "pos": [
                6963.052734375,
                300.6499938964844,
                4631.8740234375
            ],
            "ypr": [
                179.99989318847657,
                89.47884368896485,
                179.99989318847657
            ],
            "scale": 0.999997615814209,
            "enableCEPersistency": 0
        },
        {
            "name": "Land_Wall_Gate_Fen4",
            "pos": [
                6963.05078125,
                300.6499938964844,
                4633.576171875
            ],
            "ypr": [
                -179.99989318847657,
                89.46954345703125,
                -179.99989318847657
            ],
            "scale": 0.9999976754188538,
            "enableCEPersistency": 0
        },
        {
            "name": "Land_Wall_Gate_Fen4",
            "pos": [
                6959.34716796875,
                300.6499938964844,
                4626.76953125
            ],
            "ypr": [
                -179.99989318847657,
                89.484130859375,
                -179.99989318847657
            ],
            "scale": 0.9999977350234985,
            "enableCEPersistency": 0
        },
        {
            "name": "Land_Wall_Gate_Fen4",
            "pos": [
                6959.34716796875,
                300.6499938964844,
                4627.3701171875
            ],
            "ypr": [
                0.05341264605522156,
                88.558837890625,
                -179.99989318847657
            ],
            "scale": 0.9999935030937195,
            "enableCEPersistency": 0
        },
        {
            "name": "StaticObj_BusStation_wall",
            "pos": [
                6959.0087890625,
                302.20001220703127,
                4625.3486328125
            ],
            "ypr": [
                89.524658203125,
                0.0,
                0.0
            ],
            "scale": 0.9999948143959045,
            "enableCEPersistency": 0
        },
        {
            "name": "StaticObj_BusStation_wall",
            "pos": [
                6960.9111328125,
                302.20001220703127,
                4624.048828125
            ],
            "ypr": [
                0.0,
                0.0,
                0.0
            ],
            "scale": 0.9999921321868897,
            "enableCEPersistency": 0
        },
        {
            "name": "StaticObj_BusStation_wall",
            "pos": [
                6960.9111328125,
                302.20001220703127,
                4621.0458984375
            ],
            "ypr": [
                0.0,
                0.0,
                0.0
            ],
            "scale": 0.9999920129776001,
            "enableCEPersistency": 0
        },
        {
            "name": "StaticObj_BusStation_wall",
            "pos": [
                6962.21142578125,
                302.20001220703127,
                4620.2490234375
            ],
            "ypr": [
                90.0,
                0.0,
                0.0
            ],
            "scale": 0.9999914169311523,
            "enableCEPersistency": 0
        },
        {
            "name": "StaticObj_BusStation_wall",
            "pos": [
                6965.1142578125,
                302.20001220703127,
                4620.2490234375
            ],
            "ypr": [
                90.0,
                0.0,
                0.0
            ],
            "scale": 0.9999912977218628,
            "enableCEPersistency": 0
        },
        {
            "name": "StaticObj_BusStation_wall",
            "pos": [
                6967.5166015625,
                302.20001220703127,
                4620.2490234375
            ],
            "ypr": [
                90.0,
                0.0,
                0.0
            ],
            "scale": 0.999991238117218,
            "enableCEPersistency": 0
        },
        {
            "name": "StaticObj_BusStation_wall",
            "pos": [
                6970.51953125,
                302.20001220703127,
                4620.2490234375
            ],
            "ypr": [
                90.0,
                0.0,
                0.0
            ],
            "scale": 0.9999911785125732,
            "enableCEPersistency": 0
        },
        {
            "name": "StaticObj_BusStation_wall",
            "pos": [
                6973.5224609375,
                302.20001220703127,
                4620.2490234375
            ],
            "ypr": [
                90.0,
                0.0,
                0.0
            ],
            "scale": 0.9999910593032837,
            "enableCEPersistency": 0
        },
        {
            "name": "StaticObj_BusStation_wall",
            "pos": [
                6976.525390625,
                302.20001220703127,
                4620.2490234375
            ],
            "ypr": [
                90.0,
                0.0,
                0.0
            ],
            "scale": 0.9999909996986389,
            "enableCEPersistency": 0
        },
        {
            "name": "StaticObj_BusStation_wall",
            "pos": [
                6979.328125,
                302.20001220703127,
                4620.2490234375
            ],
            "ypr": [
                90.0,
                0.0,
                0.0
            ],
            "scale": 0.9999909400939941,
            "enableCEPersistency": 0
        },
        {
            "name": "StaticObj_BusStation_wall",
            "pos": [
                6979.328125,
                302.20001220703127,
                4619.94873046875
            ],
            "ypr": [
                90.0,
                0.0,
                0.0
            ],
            "scale": 0.9999908208847046,
            "enableCEPersistency": 0
        },
        {
            "name": "StaticObj_BusStation_wall",
            "pos": [
                6979.328125,
                302.20001220703127,
                4619.74853515625
            ],
            "ypr": [
                90.0,
                0.0,
                0.0
            ],
            "scale": 0.9999907612800598,
            "enableCEPersistency": 0
        },
        {
            "name": "StaticObj_BusStation_wall",
            "pos": [
                6959.609375,
                302.20001220703127,
                4625.3486328125
            ],
            "ypr": [
                89.524658203125,
                0.0,
                0.0
            ],
            "scale": 0.9999947547912598,
            "enableCEPersistency": 0
        },
        {
            "name": "StaticObj_BusStation_wall",
            "pos": [
                6959.0087890625,
                302.20001220703127,
                4628.3515625
            ],
            "ypr": [
                89.524658203125,
                0.0,
                0.0
            ],
            "scale": 0.9999947547912598,
            "enableCEPersistency": 0
        },
        {
            "name": "StaticObj_BusStation_wall",
            "pos": [
                6959.609375,
                302.20001220703127,
                4628.3515625
            ],
            "ypr": [
                89.524658203125,
                0.0,
                0.0
            ],
            "scale": 0.999994695186615,
            "enableCEPersistency": 0
        },
        {
            "name": "StaticObj_BusStation_wall",
            "pos": [
                6960.9111328125,
                302.20001220703127,
                4629.6513671875
            ],
            "ypr": [
                0.0,
                0.0,
                0.0
            ],
            "scale": 0.999993622303009,
            "enableCEPersistency": 0
        },
        {
            "name": "StaticObj_BusStation_wall",
            "pos": [
                6960.9111328125,
                302.20001220703127,
                4632.55419921875
            ],
            "ypr": [
                0.0,
                0.0,
                0.0
            ],
            "scale": 0.9999935626983643,
            "enableCEPersistency": 0
        },
        {
            "name": "StaticObj_BusStation_wall",
            "pos": [
                6962.51171875,
                302.20001220703127,
                4633.951171875
            ],
            "ypr": [
                90.0,
                0.0,
                0.0
            ],
            "scale": 0.999992847442627,
            "enableCEPersistency": 0
        },
        {
            "name": "StaticObj_BusStation_wall",
            "pos": [
                6963.41259765625,
                302.20001220703127,
                4633.951171875
            ],
            "ypr": [
                90.0,
                0.0,
                0.0
            ],
            "scale": 0.9999927282333374,
            "enableCEPersistency": 0
        },
        {
            "name": "StaticObj_Wall_FenG_Pole",
            "pos": [
                6977.1953125,
                286.3999938964844,
                4625.45166015625
            ],
            "ypr": [
                0.0,
                0.0,
                0.0
            ],
            "scale": 9.999992370605469,
            "enableCEPersistency": 0
        },
        {
            "name": "StaticObj_Wall_FenG_Pole",
            "pos": [
                6966.68505859375,
                289.3999938964844,
                4625.45166015625
            ],
            "ypr": [
                0.0,
                0.0,
                0.0
            ],
            "scale": 9.999992370605469,
            "enableCEPersistency": 0
        },
        {
            "name": "StaticObj_Wall_FenG_Pole",
            "pos": [
                6977.1953125,
                286.3999938964844,
                4635.76171875
            ],
            "ypr": [
                0.0,
                0.0,
                0.0
            ],
            "scale": 9.999992370605469,
            "enableCEPersistency": 0
        },
        {
            "name": "StaticObj_Wall_FenG_Pole",
            "pos": [
                6966.68505859375,
                289.3999938964844,
                4635.76171875
            ],
            "ypr": [
                0.0,
                0.0,
                0.0
            ],
            "scale": 9.999992370605469,
            "enableCEPersistency": 0
        },
        {
            "name": "StaticObj_Roadblock_Wood_Small",
            "pos": [
                6961.9599609375,
                301.3399963378906,
                4624.18017578125
            ],
            "ypr": [
                -22.918397903442384,
                0.0,
                0.0
            ],
            "scale": 0.9999969601631165,
            "enableCEPersistency": 0
        },
        {
            "name": "StaticObj_Roadblock_Wood_Small",
            "pos": [
                6984.18359375,
                301.3268127441406,
                4592.14404296875
            ],
            "ypr": [
                22.91839027404785,
                -0.0,
                -0.0
            ],
            "scale": 0.9999977350234985,
            "enableCEPersistency": 0
        },
        {
            "name": "StaticObj_Roadblock_Wood_Small",
            "pos": [
                6984.18359375,
                301.3268127441406,
                4595.2470703125
            ],
            "ypr": [
                -22.918392181396486,
                -0.0,
                -0.0
            ],
            "scale": 0.999997079372406,
            "enableCEPersistency": 0
        },
        {
            "name": "Land_Wall_Gate_Fen4",
            "pos": [
                6982.8701171875,
                299.5,
                4594.23974609375
            ],
            "ypr": [
                -179.9999542236328,
                14.999868392944336,
                18.000001907348634
            ],
            "scale": 0.9999972581863403,
            "enableCEPersistency": 0
        },
        {
            "name": "StaticObj_BusStation_wall",
            "pos": [
                6985.1015625,
                302.20001220703127,
                4621.25
            ],
            "ypr": [
                0.0,
                0.0,
                0.0
            ],
            "scale": 0.9999886155128479,
            "enableCEPersistency": 0
        },
        {
            "name": "StaticObj_BusStation_wall",
            "pos": [
                6985.1015625,
                302.20001220703127,
                4622.55126953125
            ],
            "ypr": [
                0.0,
                0.0,
                0.0
            ],
            "scale": 0.9999885559082031,
            "enableCEPersistency": 0
        },
        {
            "name": "StaticObj_Platform1_Block",
            "pos": [
                6953.37060546875,
                318.0,
                4634.330078125
            ],
            "ypr": [
                0.0,
                0.0,
                0.0
            ],
            "scale": 0.9999990463256836,
            "enableCEPersistency": 0
        },
        {
            "name": "StaticObj_Platform1_Block",
            "pos": [
                6950.669921875,
                318.0,
                4634.330078125
            ],
            "ypr": [
                0.0,
                0.0,
                0.0
            ],
            "scale": 0.9999986886978149,
            "enableCEPersistency": 0
        },
        {
            "name": "StaticObj_Platform1_Block",
            "pos": [
                6963.8828125,
                318.0,
                4628.02392578125
            ],
            "ypr": [
                0.0,
                0.0,
                0.0
            ],
            "scale": 0.9999985694885254,
            "enableCEPersistency": 0
        },
        {
            "name": "StaticObj_Wall_IndCnc4_Low_8",
            "pos": [
                6972.7099609375,
                327.0,
                4648.25
            ],
            "ypr": [
                -180.0,
                90.0,
                -180.0
            ],
            "scale": 14.999995231628418,
            "enableCEPersistency": 0
        },
        {
            "name": "StaticObj_Wall_IndCnc4_Low_8",
            "pos": [
                6972.7099609375,
                327.0,
                4609.31201171875
            ],
            "ypr": [
                -0.000005008955668017734,
                90.0,
                -0.000005008955668017734
            ],
            "scale": 14.999994277954102,
            "enableCEPersistency": 0
        },
        {
            "name": "StaticObj_Wall_IndCnc4_Low_8",
            "pos": [
                6972.7099609375,
                327.0,
                4578.58203125
            ],
            "ypr": [
                179.99998474121095,
                90.0,
                179.99998474121095
            ],
            "scale": 14.999993324279786,
            "enableCEPersistency": 0
        },
        {
            "name": "StaticObj_Wall_IndCnc4_Low_8",
            "pos": [
                6972.7099609375,
                327.0,
                4548.65283203125
            ],
            "ypr": [
                -0.00002231179860245902,
                90.0,
                -0.00002231179860245902
            ],
            "scale": 14.999994277954102,
            "enableCEPersistency": 0
        },
        {
            "name": "StaticObj_Wall_IndCnc4_Low_8",
            "pos": [
                6972.7099609375,
                327.0,
                4518.82373046875
            ],
            "ypr": [
                179.99996948242188,
                90.0,
                179.99996948242188
            ],
            "scale": 14.999993324279786,
            "enableCEPersistency": 0
        },
        {
            "name": "StaticObj_Wall_IndCnc4_Low_8",
            "pos": [
                6972.60986328125,
                327.0,
                4487.99365234375
            ],
            "ypr": [
                -0.000035972174373455349,
                90.0,
                -0.000035972174373455349
            ],
            "scale": 14.999994277954102,
            "enableCEPersistency": 0
        },
        {
            "name": "StaticObj_Wall_IndCnc4_Low_8",
            "pos": [
                6972.7099609375,
                314.0,
                4661.259765625
            ],
            "ypr": [
                0.0,
                0.0,
                0.0
            ],
            "scale": 14.99998950958252,
            "enableCEPersistency": 0
        },
        {
            "name": "StaticObj_Wall_IndCnc4_Low_8",
            "pos": [
                6958.2958984375,
                300.0,
                4661.259765625
            ],
            "ypr": [
                0.0,
                0.0,
                0.0
            ],
            "scale": 14.99998950958252,
            "enableCEPersistency": 0
        },
        {
            "name": "StaticObj_Wall_IndCnc4_Low_8",
            "pos": [
                7030.26611328125,
                300.0,
                4583.28369140625
            ],
            "ypr": [
                90.0,
                0.0,
                0.0
            ],
            "scale": 14.99998950958252,
            "enableCEPersistency": 0
        },
        {
            "name": "StaticObj_Wall_IndCnc4_Low_8",
            "pos": [
                7030.27001953125,
                314.0,
                4598.39990234375
            ],
            "ypr": [
                90.0,
                0.0,
                0.0
            ],
            "scale": 14.99998950958252,
            "enableCEPersistency": 0
        },
        {
            "name": "StaticObj_Wall_IndCnc4_Low_8",
            "pos": [
                7030.26611328125,
                300.0,
                4532.43408203125
            ],
            "ypr": [
                90.0,
                0.0,
                0.0
            ],
            "scale": 14.99998950958252,
            "enableCEPersistency": 0
        },
        {
            "name": "StaticObj_Wall_IndCnc4_Low_8",
            "pos": [
                7030.27001953125,
                314.0,
                4532.435546875
            ],
            "ypr": [
                90.0,
                0.0,
                0.0
            ],
            "scale": 14.99998950958252,
            "enableCEPersistency": 0
        },
        {
            "name": "StaticObj_Wall_IndCnc4_Low_8",
            "pos": [
                6972.7099609375,
                314.0,
                4475.17822265625
            ],
            "ypr": [
                0.0,
                0.0,
                0.0
            ],
            "scale": 14.99998950958252,
            "enableCEPersistency": 0
        },
        {
            "name": "StaticObj_Wall_IndCnc4_Low_8",
            "pos": [
                6915.15771484375,
                314.0,
                4598.39990234375
            ],
            "ypr": [
                90.0,
                0.0,
                0.0
            ],
            "scale": 14.99998950958252,
            "enableCEPersistency": 0
        },
        {
            "name": "StaticObj_Wall_IndCnc4_Low_8",
            "pos": [
                6915.15771484375,
                314.0,
                4532.435546875
            ],
            "ypr": [
                90.0,
                0.0,
                0.0
            ],
            "scale": 14.99998950958252,
            "enableCEPersistency": 0
        },
        {
            "name": "StaticObj_Wall_IndCnc4_Low_8",
            "pos": [
                6988.02001953125,
                327.8999938964844,
                4632.43017578125
            ],
            "ypr": [
                -180.0,
                90.0,
                -180.0
            ],
            "scale": 9.999992370605469,
            "enableCEPersistency": 0
        },
        {
            "name": "StaticObj_Wall_IndCnc4_Low_8",
            "pos": [
                6962.0078125,
                328.79998779296877,
                4629.1298828125
            ],
            "ypr": [
                -0.000005008955668017734,
                90.0,
                -0.000005008955668017734
            ],
            "scale": 4.999998092651367,
            "enableCEPersistency": 0
        },
        {
            "name": "StaticObj_Wall_IndCnc4_Low_8",
            "pos": [
                6915.46240234375,
                328.79998779296877,
                4629.1298828125
            ],
            "ypr": [
                179.99998474121095,
                90.0,
                179.99998474121095
            ],
            "scale": 4.999997615814209,
            "enableCEPersistency": 0
        },
        {
            "name": "StaticObj_Wall_IndCnc4_Low_8",
            "pos": [
                7050.279296875,
                289.0,
                4660.05712890625
            ],
            "ypr": [
                141.2762908935547,
                0.0,
                0.0
            ],
            "scale": 6.999957084655762,
            "enableCEPersistency": 0
        },
        {
            "name": "StaticObj_Wall_IndCnc4_Low_8",
            "pos": [
                7041.37060546875,
                289.0,
                4674.37109375
            ],
            "ypr": [
                148.29534912109376,
                0.0,
                0.0
            ],
            "scale": 6.999938488006592,
            "enableCEPersistency": 0
        },
        {
            "name": "StaticObj_Wall_IndCnc4_Low_8",
            "pos": [
                7041.86669921875,
                297.0,
                4664.45751953125
            ],
            "ypr": [
                -35.00599670410156,
                90.0,
                -180.0
            ],
            "scale": 9.0,
            "enableCEPersistency": 0
        },
        {
            "name": "StaticObj_Wall_IndCnc4_Low_8",
            "pos": [
                7066.1982421875,
                289.8999938964844,
                4682.9208984375
            ],
            "ypr": [
                -108.139892578125,
                90.0,
                15.000004768371582
            ],
            "scale": 2.9999759197235109,
            "enableCEPersistency": 0
        },
        {
            "name": "Land_Underground_Panel",
            "pos": [
                7080.509765625,
                292.0,
                4688.5
            ],
            "ypr": [
                -126.62399291992188,
                0.0,
                0.0
            ],
            "scale": 0.9999918937683106,
            "enableCEPersistency": 0
        },
        {
            "name": "Land_Underground_Panel_Lever",
            "pos": [
                6935.580078125,
                332.25,
                4630.580078125
            ],
            "ypr": [
                0.0,
                0.0,
                0.0
            ],
            "scale": 0.999998927116394,
            "enableCEPersistency": 0
        }
    ]
}