{
    "Objects": [
        {
            "name": "Land_Roadblock_Table",
            "pos": [
                10795.7001953125,
                197.10000610351563,
                10980.2001953125
            ],
            "ypr": [
                -44.976890563964847,
                0.0,
                0.0
            ],
            "scale": 1.0,
            "enableCEPersistency": 0
        },
        {
            "name": "NailBox",
            "pos": [
                10796.5,
                197.5,
                10980.599609375
            ],
            "ypr": [
                -44.976890563964847,
                0.0,
                0.0
            ],
            "scale": 1.0,
            "enableCEPersistency": 0
        },
        {
            "name": "Pliers",
            "pos": [
                10796.2939453125,
                197.50999450683595,
                10980.482421875
            ],
            "ypr": [
                135.99996948242188,
                75.99907684326172,
                179.99998474121095
            ],
            "scale": 1.0,
            "enableCEPersistency": 0
        },
        {
            "name": "BarbedWire",
            "pos": [
                10796.099609375,
                197.47999572753907,
                10980.2001953125
            ],
            "ypr": [
                47.125701904296878,
                0.0,
                0.0
            ],
            "scale": 1.0,
            "enableCEPersistency": 0
        },
        {
            "name": "Hammer",
            "pos": [
                10795.53515625,
                197.52000427246095,
                10979.8095703125
            ],
            "ypr": [
                135.0,
                89.8880844116211,
                179.99998474121095
            ],
            "scale": 1.0,
            "enableCEPersistency": 0
        },
        {
            "name": "Pickaxe",
            "pos": [
                10795.1416015625,
                196.89999389648438,
                10979.2998046875
            ],
            "ypr": [
                -45.0,
                0.0,
                0.0
            ],
            "scale": 1.0,
            "enableCEPersistency": 0
        },
        {
            "name": "FenceKit",
            "pos": [
                10795.28515625,
                197.5399932861328,
                10979.55078125
            ],
            "ypr": [
                134.1632843017578,
                89.42290496826172,
                179.99989318847657
            ],
            "scale": 1.0,
            "enableCEPersistency": 0
        },
        {
            "name": "WatchtowerKit",
            "pos": [
                10795.1875,
                197.5399932861328,
                10979.4619140625
            ],
            "ypr": [
                135.0,
                89.8658218383789,
                179.99998474121095
            ],
            "scale": 0.9999998807907105,
            "enableCEPersistency": 0
        },
        {
            "name": "Whetstone",
            "pos": [
                10795.5087890625,
                197.5,
                10979.541015625
            ],
            "ypr": [
                45.0,
                0.0,
                0.0
            ],
            "scale": 1.0,
            "enableCEPersistency": 0
        },
        {
            "name": "PileOfWoodenPlanks",
            "pos": [
                10793.33203125,
                196.6999969482422,
                10978.0
            ],
            "ypr": [
                -47.12564468383789,
                0.0,
                0.0
            ],
            "scale": 0.9999999403953552,
            "enableCEPersistency": 0
        },
        {
            "name": "MetalPlate",
            "pos": [
                10791.5,
                196.6999969482422,
                10975.7998046875
            ],
            "ypr": [
                44.833900451660159,
                0.0,
                0.0
            ],
            "scale": 1.0,
            "enableCEPersistency": 0
        },
        {
            "name": "WoodenLog",
            "pos": [
                10791.0,
                196.6999969482422,
                10975.099609375
            ],
            "ypr": [
                -45.83659744262695,
                0.0,
                0.0
            ],
            "scale": 1.0,
            "enableCEPersistency": 0
        },
        {
            "name": "WoodenLog",
            "pos": [
                10790.87109375,
                196.6999969482422,
                10974.947265625
            ],
            "ypr": [
                -45.836585998535159,
                0.0,
                0.0
            ],
            "scale": 1.0,
            "enableCEPersistency": 0
        },
        {
            "name": "WoodenLog",
            "pos": [
                10790.748046875,
                196.6999969482422,
                10974.818359375
            ],
            "ypr": [
                -45.836585998535159,
                0.0,
                0.0
            ],
            "scale": 1.0,
            "enableCEPersistency": 0
        },
        {
            "name": "WoodenLog",
            "pos": [
                10790.619140625,
                196.6999969482422,
                10974.666015625
            ],
            "ypr": [
                -45.836585998535159,
                0.0,
                0.0
            ],
            "scale": 1.0,
            "enableCEPersistency": 0
        },
        {
            "name": "WoodenLog",
            "pos": [
                10790.3701171875,
                196.6999969482422,
                10974.37890625
            ],
            "ypr": [
                -45.836585998535159,
                0.0,
                0.0
            ],
            "scale": 1.0,
            "enableCEPersistency": 0
        },
        {
            "name": "WoodenLog",
            "pos": [
                10790.4990234375,
                196.6999969482422,
                10974.53125
            ],
            "ypr": [
                -45.836585998535159,
                0.0,
                0.0
            ],
            "scale": 1.0,
            "enableCEPersistency": 0
        },
        {
            "name": "CombinationLock4",
            "pos": [
                10795.8330078125,
                197.5,
                10979.8759765625
            ],
            "ypr": [
                0.0,
                0.0,
                0.0
            ],
            "scale": 1.0,
            "enableCEPersistency": 0
        },
        {
            "name": "CombinationLock4",
            "pos": [
                10795.7919921875,
                197.5,
                10979.92578125
            ],
            "ypr": [
                0.0,
                0.0,
                0.0
            ],
            "scale": 1.0,
            "enableCEPersistency": 0
        },
        {
            "name": "NailBox",
            "pos": [
                10796.458984375,
                197.5,
                10980.6494140625
            ],
            "ypr": [
                -44.976890563964847,
                0.0,
                0.0
            ],
            "scale": 1.0,
            "enableCEPersistency": 0
        },
        {
            "name": "Pliers",
            "pos": [
                10796.2529296875,
                197.50999450683595,
                10980.5322265625
            ],
            "ypr": [
                135.9999542236328,
                75.99809265136719,
                179.99996948242188
            ],
            "scale": 1.0,
            "enableCEPersistency": 0
        },
        {
            "name": "BarbedWire",
            "pos": [
                10796.05859375,
                197.47999572753907,
                10980.25
            ],
            "ypr": [
                47.125701904296878,
                0.0,
                0.0
            ],
            "scale": 1.0,
            "enableCEPersistency": 0
        },
        {
            "name": "Hammer",
            "pos": [
                10795.494140625,
                197.52000427246095,
                10979.859375
            ],
            "ypr": [
                135.0,
                89.83807373046875,
                179.99996948242188
            ],
            "scale": 1.0,
            "enableCEPersistency": 0
        },
        {
            "name": "Pickaxe",
            "pos": [
                10795.1005859375,
                196.89999389648438,
                10979.349609375
            ],
            "ypr": [
                -45.0,
                0.0,
                0.0
            ],
            "scale": 1.0,
            "enableCEPersistency": 0
        },
        {
            "name": "FenceKit",
            "pos": [
                10795.244140625,
                197.5399932861328,
                10979.6005859375
            ],
            "ypr": [
                134.1632843017578,
                89.40520477294922,
                179.99989318847657
            ],
            "scale": 0.9999999403953552,
            "enableCEPersistency": 0
        },
        {
            "name": "WatchtowerKit",
            "pos": [
                10795.146484375,
                197.5399932861328,
                10979.51171875
            ],
            "ypr": [
                135.0,
                89.81336975097656,
                179.99996948242188
            ],
            "scale": 1.0,
            "enableCEPersistency": 0
        },
        {
            "name": "Whetstone",
            "pos": [
                10795.4677734375,
                197.5,
                10979.5908203125
            ],
            "ypr": [
                45.0,
                0.0,
                0.0
            ],
            "scale": 1.0,
            "enableCEPersistency": 0
        },
        {
            "name": "CombinationLock4",
            "pos": [
                10795.7216796875,
                197.5,
                10979.99609375
            ],
            "ypr": [
                0.0,
                0.0,
                0.0
            ],
            "scale": 1.0,
            "enableCEPersistency": 0
        },
        {
            "name": "NailBox",
            "pos": [
                10796.388671875,
                197.5,
                10980.7197265625
            ],
            "ypr": [
                -44.976890563964847,
                0.0,
                0.0
            ],
            "scale": 1.0,
            "enableCEPersistency": 0
        },
        {
            "name": "Pliers",
            "pos": [
                10796.1826171875,
                197.50999450683595,
                10980.6025390625
            ],
            "ypr": [
                135.99993896484376,
                75.99712371826172,
                179.9999542236328
            ],
            "scale": 1.0,
            "enableCEPersistency": 0
        },
        {
            "name": "BarbedWire",
            "pos": [
                10795.98828125,
                197.47999572753907,
                10980.3203125
            ],
            "ypr": [
                47.125701904296878,
                0.0,
                0.0
            ],
            "scale": 1.0,
            "enableCEPersistency": 0
        },
        {
            "name": "Hammer",
            "pos": [
                10795.423828125,
                197.52000427246095,
                10979.9296875
            ],
            "ypr": [
                135.0,
                89.79922485351563,
                179.9999542236328
            ],
            "scale": 1.0,
            "enableCEPersistency": 0
        },
        {
            "name": "Pickaxe",
            "pos": [
                10795.0302734375,
                196.89999389648438,
                10979.419921875
            ],
            "ypr": [
                -45.0,
                0.0,
                0.0
            ],
            "scale": 1.0,
            "enableCEPersistency": 0
        },
        {
            "name": "FenceKit",
            "pos": [
                10795.173828125,
                197.5399932861328,
                10979.6708984375
            ],
            "ypr": [
                134.1632843017578,
                89.38866424560547,
                179.99989318847657
            ],
            "scale": 1.0,
            "enableCEPersistency": 0
        },
        {
            "name": "WatchtowerKit",
            "pos": [
                10795.076171875,
                197.5399932861328,
                10979.58203125
            ],
            "ypr": [
                135.0,
                89.77100372314453,
                179.9999542236328
            ],
            "scale": 1.0,
            "enableCEPersistency": 0
        },
        {
            "name": "Whetstone",
            "pos": [
                10795.3974609375,
                197.5,
                10979.6611328125
            ],
            "ypr": [
                45.0,
                0.0,
                0.0
            ],
            "scale": 1.0,
            "enableCEPersistency": 0
        },
        {
            "name": "CombinationLock4",
            "pos": [
                10795.6513671875,
                197.5,
                10980.0693359375
            ],
            "ypr": [
                0.0,
                0.0,
                0.0
            ],
            "scale": 1.0,
            "enableCEPersistency": 0
        },
        {
            "name": "NailBox",
            "pos": [
                10796.318359375,
                197.5,
                10980.79296875
            ],
            "ypr": [
                -44.976890563964847,
                0.0,
                0.0
            ],
            "scale": 1.0,
            "enableCEPersistency": 0
        },
        {
            "name": "Pliers",
            "pos": [
                10796.1123046875,
                197.50999450683595,
                10980.67578125
            ],
            "ypr": [
                135.99993896484376,
                75.99607849121094,
                179.99993896484376
            ],
            "scale": 1.0,
            "enableCEPersistency": 0
        },
        {
            "name": "BarbedWire",
            "pos": [
                10795.91796875,
                197.47999572753907,
                10980.3935546875
            ],
            "ypr": [
                47.125701904296878,
                0.0,
                0.0
            ],
            "scale": 1.0,
            "enableCEPersistency": 0
        },
        {
            "name": "Hammer",
            "pos": [
                10795.353515625,
                197.52000427246095,
                10980.0029296875
            ],
            "ypr": [
                135.0,
                89.76509094238281,
                179.99993896484376
            ],
            "scale": 0.9999999403953552,
            "enableCEPersistency": 0
        },
        {
            "name": "Pickaxe",
            "pos": [
                10794.9599609375,
                196.89999389648438,
                10979.4931640625
            ],
            "ypr": [
                -45.0,
                0.0,
                0.0
            ],
            "scale": 1.0,
            "enableCEPersistency": 0
        },
        {
            "name": "FenceKit",
            "pos": [
                10795.103515625,
                197.5399932861328,
                10979.744140625
            ],
            "ypr": [
                134.1632843017578,
                89.37191772460938,
                179.99989318847657
            ],
            "scale": 1.0,
            "enableCEPersistency": 0
        },
        {
            "name": "WatchtowerKit",
            "pos": [
                10795.005859375,
                197.5399932861328,
                10979.6552734375
            ],
            "ypr": [
                135.0,
                89.73384857177735,
                179.99993896484376
            ],
            "scale": 1.0,
            "enableCEPersistency": 0
        },
        {
            "name": "Whetstone",
            "pos": [
                10795.3271484375,
                197.5,
                10979.734375
            ],
            "ypr": [
                45.0,
                0.0,
                0.0
            ],
            "scale": 1.0,
            "enableCEPersistency": 0
        },
        {
            "name": "CombinationLock4",
            "pos": [
                10795.5927734375,
                197.5,
                10980.130859375
            ],
            "ypr": [
                0.0,
                0.0,
                0.0
            ],
            "scale": 1.0,
            "enableCEPersistency": 0
        },
        {
            "name": "NailBox",
            "pos": [
                10796.259765625,
                197.5,
                10980.8544921875
            ],
            "ypr": [
                -44.976890563964847,
                0.0,
                0.0
            ],
            "scale": 1.0,
            "enableCEPersistency": 0
        },
        {
            "name": "Pliers",
            "pos": [
                10796.0537109375,
                197.50999450683595,
                10980.7373046875
            ],
            "ypr": [
                135.99993896484376,
                75.99504089355469,
                179.9999237060547
            ],
            "scale": 1.0,
            "enableCEPersistency": 0
        },
        {
            "name": "BarbedWire",
            "pos": [
                10795.859375,
                197.47999572753907,
                10980.455078125
            ],
            "ypr": [
                47.125701904296878,
                0.0,
                0.0
            ],
            "scale": 1.0,
            "enableCEPersistency": 0
        },
        {
            "name": "Hammer",
            "pos": [
                10795.294921875,
                197.52000427246095,
                10980.064453125
            ],
            "ypr": [
                135.0,
                89.73680877685547,
                179.9999237060547
            ],
            "scale": 1.0,
            "enableCEPersistency": 0
        },
        {
            "name": "Pickaxe",
            "pos": [
                10794.9013671875,
                196.89999389648438,
                10979.5546875
            ],
            "ypr": [
                -45.0,
                0.0,
                0.0
            ],
            "scale": 1.0,
            "enableCEPersistency": 0
        },
        {
            "name": "FenceKit",
            "pos": [
                10795.044921875,
                197.5399932861328,
                10979.8056640625
            ],
            "ypr": [
                134.1632843017578,
                89.3556137084961,
                179.99989318847657
            ],
            "scale": 0.9999999403953552,
            "enableCEPersistency": 0
        },
        {
            "name": "WatchtowerKit",
            "pos": [
                10794.947265625,
                197.5399932861328,
                10979.716796875
            ],
            "ypr": [
                135.0,
                89.69802856445313,
                179.9999237060547
            ],
            "scale": 0.9999999403953552,
            "enableCEPersistency": 0
        },
        {
            "name": "Whetstone",
            "pos": [
                10795.2685546875,
                197.5,
                10979.7958984375
            ],
            "ypr": [
                45.0,
                0.0,
                0.0
            ],
            "scale": 1.0,
            "enableCEPersistency": 0
        },
        {
            "name": "BarbedWire",
            "pos": [
                10795.7919921875,
                197.47999572753907,
                10980.51953125
            ],
            "ypr": [
                47.125701904296878,
                0.0,
                0.0
            ],
            "scale": 1.0,
            "enableCEPersistency": 0
        },
        {
            "name": "Hammer",
            "pos": [
                10795.2275390625,
                197.52000427246095,
                10980.12890625
            ],
            "ypr": [
                135.0,
                89.7079086303711,
                179.99990844726563
            ],
            "scale": 1.0,
            "enableCEPersistency": 0
        },
        {
            "name": "Pickaxe",
            "pos": [
                10794.833984375,
                196.89999389648438,
                10979.619140625
            ],
            "ypr": [
                -45.0,
                0.0,
                0.0
            ],
            "scale": 1.0,
            "enableCEPersistency": 0
        },
        {
            "name": "FenceKit",
            "pos": [
                10794.9775390625,
                197.5399932861328,
                10979.8701171875
            ],
            "ypr": [
                134.1632843017578,
                89.33943176269531,
                179.99989318847657
            ],
            "scale": 0.9999999403953552,
            "enableCEPersistency": 0
        },
        {
            "name": "WatchtowerKit",
            "pos": [
                10794.8798828125,
                197.5399932861328,
                10979.78125
            ],
            "ypr": [
                135.0,
                89.66780090332031,
                179.99990844726563
            ],
            "scale": 1.0,
            "enableCEPersistency": 0
        },
        {
            "name": "Whetstone",
            "pos": [
                10795.201171875,
                197.5,
                10979.8603515625
            ],
            "ypr": [
                45.0,
                0.0,
                0.0
            ],
            "scale": 1.0,
            "enableCEPersistency": 0
        },
        {
            "name": "CombinationLock4",
            "pos": [
                10795.525390625,
                197.5,
                10980.1953125
            ],
            "ypr": [
                0.0,
                0.0,
                0.0
            ],
            "scale": 1.0,
            "enableCEPersistency": 0
        },
        {
            "name": "NailBox",
            "pos": [
                10796.1923828125,
                197.5,
                10980.9189453125
            ],
            "ypr": [
                -44.976890563964847,
                0.0,
                0.0
            ],
            "scale": 1.0,
            "enableCEPersistency": 0
        },
        {
            "name": "Pliers",
            "pos": [
                10795.986328125,
                197.50999450683595,
                10980.8017578125
            ],
            "ypr": [
                135.99993896484376,
                75.99394989013672,
                179.99990844726563
            ],
            "scale": 1.0,
            "enableCEPersistency": 0
        },
        {
            "name": "BarbedWire",
            "pos": [
                10795.7392578125,
                197.47999572753907,
                10980.5693359375
            ],
            "ypr": [
                47.125701904296878,
                0.0,
                0.0
            ],
            "scale": 1.0,
            "enableCEPersistency": 0
        },
        {
            "name": "Hammer",
            "pos": [
                10795.1748046875,
                197.52000427246095,
                10980.1787109375
            ],
            "ypr": [
                135.0,
                89.68162536621094,
                179.99989318847657
            ],
            "scale": 1.0,
            "enableCEPersistency": 0
        },
        {
            "name": "Pickaxe",
            "pos": [
                10794.78125,
                196.89999389648438,
                10979.6689453125
            ],
            "ypr": [
                -45.0,
                0.0,
                0.0
            ],
            "scale": 1.0,
            "enableCEPersistency": 0
        },
        {
            "name": "FenceKit",
            "pos": [
                10794.9248046875,
                197.5399932861328,
                10979.919921875
            ],
            "ypr": [
                134.1632843017578,
                89.32362365722656,
                179.99989318847657
            ],
            "scale": 1.0,
            "enableCEPersistency": 0
        },
        {
            "name": "WatchtowerKit",
            "pos": [
                10794.8271484375,
                197.5399932861328,
                10979.8310546875
            ],
            "ypr": [
                135.0,
                89.63845825195313,
                179.99989318847657
            ],
            "scale": 1.0,
            "enableCEPersistency": 0
        },
        {
            "name": "Whetstone",
            "pos": [
                10795.1484375,
                197.5,
                10979.91015625
            ],
            "ypr": [
                45.0,
                0.0,
                0.0
            ],
            "scale": 1.0,
            "enableCEPersistency": 0
        },
        {
            "name": "CombinationLock4",
            "pos": [
                10795.47265625,
                197.5,
                10980.2451171875
            ],
            "ypr": [
                0.0,
                0.0,
                0.0
            ],
            "scale": 1.0,
            "enableCEPersistency": 0
        },
        {
            "name": "NailBox",
            "pos": [
                10796.1396484375,
                197.5,
                10980.96875
            ],
            "ypr": [
                -44.976890563964847,
                0.0,
                0.0
            ],
            "scale": 1.0,
            "enableCEPersistency": 0
        },
        {
            "name": "Pliers",
            "pos": [
                10795.93359375,
                197.50999450683595,
                10980.8515625
            ],
            "ypr": [
                135.99993896484376,
                75.99284362792969,
                179.99989318847657
            ],
            "scale": 1.0,
            "enableCEPersistency": 0
        },
        {
            "name": "MetalPlate",
            "pos": [
                10791.5,
                196.6999969482422,
                10975.7998046875
            ],
            "ypr": [
                44.833900451660159,
                0.0,
                0.0
            ],
            "scale": 1.0,
            "enableCEPersistency": 0
        },
        {
            "name": "MetalPlate",
            "pos": [
                10791.5,
                196.6999969482422,
                10975.7998046875
            ],
            "ypr": [
                44.833900451660159,
                0.0,
                0.0
            ],
            "scale": 1.0,
            "enableCEPersistency": 0
        },
        {
            "name": "MetalPlate",
            "pos": [
                10791.5,
                196.6999969482422,
                10975.7998046875
            ],
            "ypr": [
                44.833900451660159,
                0.0,
                0.0
            ],
            "scale": 1.0,
            "enableCEPersistency": 0
        },
        {
            "name": "MetalPlate",
            "pos": [
                10791.5,
                196.6999969482422,
                10975.7998046875
            ],
            "ypr": [
                44.833900451660159,
                0.0,
                0.0
            ],
            "scale": 1.0,
            "enableCEPersistency": 0
        },
        {
            "name": "MetalPlate",
            "pos": [
                10791.5,
                196.6999969482422,
                10975.7998046875
            ],
            "ypr": [
                44.833900451660159,
                0.0,
                0.0
            ],
            "scale": 1.0,
            "enableCEPersistency": 0
        },
        {
            "name": "MetalPlate",
            "pos": [
                10791.5,
                196.6999969482422,
                10975.7998046875
            ],
            "ypr": [
                44.833900451660159,
                0.0,
                0.0
            ],
            "scale": 1.0,
            "enableCEPersistency": 0
        },
        {
            "name": "MetalPlate",
            "pos": [
                10791.5,
                196.6999969482422,
                10975.7998046875
            ],
            "ypr": [
                44.833900451660159,
                0.0,
                0.0
            ],
            "scale": 1.0,
            "enableCEPersistency": 0
        },
        {
            "name": "MetalPlate",
            "pos": [
                10791.5,
                196.6999969482422,
                10975.7998046875
            ],
            "ypr": [
                44.833900451660159,
                0.0,
                0.0
            ],
            "scale": 1.0,
            "enableCEPersistency": 0
        },
        {
            "name": "MetalPlate",
            "pos": [
                10791.5,
                196.6999969482422,
                10975.7998046875
            ],
            "ypr": [
                44.833900451660159,
                0.0,
                0.0
            ],
            "scale": 1.0,
            "enableCEPersistency": 0
        },
        {
            "name": "MetalPlate",
            "pos": [
                10791.5,
                196.6999969482422,
                10975.7998046875
            ],
            "ypr": [
                44.833900451660159,
                0.0,
                0.0
            ],
            "scale": 1.0,
            "enableCEPersistency": 0
        },
        {
            "name": "MetalPlate",
            "pos": [
                10791.5,
                196.6999969482422,
                10975.7998046875
            ],
            "ypr": [
                44.833900451660159,
                0.0,
                0.0
            ],
            "scale": 1.0,
            "enableCEPersistency": 0
        },
        {
            "name": "MetalPlate",
            "pos": [
                10791.5,
                196.6999969482422,
                10975.7998046875
            ],
            "ypr": [
                44.833900451660159,
                0.0,
                0.0
            ],
            "scale": 1.0,
            "enableCEPersistency": 0
        },
        {
            "name": "WoodenLog",
            "pos": [
                10791.0,
                196.6999969482422,
                10975.099609375
            ],
            "ypr": [
                -45.836585998535159,
                0.0,
                0.0
            ],
            "scale": 1.0,
            "enableCEPersistency": 0
        },
        {
            "name": "WoodenLog",
            "pos": [
                10790.87109375,
                196.6999969482422,
                10974.947265625
            ],
            "ypr": [
                -45.836585998535159,
                0.0,
                0.0
            ],
            "scale": 1.0,
            "enableCEPersistency": 0
        },
        {
            "name": "WoodenLog",
            "pos": [
                10790.748046875,
                196.6999969482422,
                10974.818359375
            ],
            "ypr": [
                -45.836585998535159,
                0.0,
                0.0
            ],
            "scale": 1.0,
            "enableCEPersistency": 0
        },
        {
            "name": "WoodenLog",
            "pos": [
                10790.619140625,
                196.6999969482422,
                10974.666015625
            ],
            "ypr": [
                -45.836585998535159,
                0.0,
                0.0
            ],
            "scale": 1.0,
            "enableCEPersistency": 0
        },
        {
            "name": "WoodenLog",
            "pos": [
                10790.3701171875,
                196.6999969482422,
                10974.37890625
            ],
            "ypr": [
                -45.836585998535159,
                0.0,
                0.0
            ],
            "scale": 1.0,
            "enableCEPersistency": 0
        },
        {
            "name": "WoodenLog",
            "pos": [
                10790.4990234375,
                196.6999969482422,
                10974.53125
            ],
            "ypr": [
                -45.836585998535159,
                0.0,
                0.0
            ],
            "scale": 1.0,
            "enableCEPersistency": 0
        },
        {
            "name": "WoodenLog",
            "pos": [
                10791.0,
                196.6999969482422,
                10975.099609375
            ],
            "ypr": [
                -45.836585998535159,
                0.0,
                0.0
            ],
            "scale": 1.0,
            "enableCEPersistency": 0
        },
        {
            "name": "WoodenLog",
            "pos": [
                10790.87109375,
                196.6999969482422,
                10974.947265625
            ],
            "ypr": [
                -45.836585998535159,
                0.0,
                0.0
            ],
            "scale": 1.0,
            "enableCEPersistency": 0
        },
        {
            "name": "WoodenLog",
            "pos": [
                10790.748046875,
                196.6999969482422,
                10974.818359375
            ],
            "ypr": [
                -45.836585998535159,
                0.0,
                0.0
            ],
            "scale": 1.0,
            "enableCEPersistency": 0
        },
        {
            "name": "WoodenLog",
            "pos": [
                10790.619140625,
                196.6999969482422,
                10974.666015625
            ],
            "ypr": [
                -45.836585998535159,
                0.0,
                0.0
            ],
            "scale": 1.0,
            "enableCEPersistency": 0
        },
        {
            "name": "WoodenLog",
            "pos": [
                10790.3701171875,
                196.6999969482422,
                10974.37890625
            ],
            "ypr": [
                -45.836585998535159,
                0.0,
                0.0
            ],
            "scale": 1.0,
            "enableCEPersistency": 0
        },
        {
            "name": "WoodenLog",
            "pos": [
                10790.4990234375,
                196.6999969482422,
                10974.53125
            ],
            "ypr": [
                -45.836585998535159,
                0.0,
                0.0
            ],
            "scale": 1.0,
            "enableCEPersistency": 0
        },
        {
            "name": "WoodenLog",
            "pos": [
                10791.0,
                196.6999969482422,
                10975.099609375
            ],
            "ypr": [
                -45.836585998535159,
                0.0,
                0.0
            ],
            "scale": 1.0,
            "enableCEPersistency": 0
        },
        {
            "name": "WoodenLog",
            "pos": [
                10790.87109375,
                196.6999969482422,
                10974.947265625
            ],
            "ypr": [
                -45.836585998535159,
                0.0,
                0.0
            ],
            "scale": 1.0,
            "enableCEPersistency": 0
        },
        {
            "name": "WoodenLog",
            "pos": [
                10790.748046875,
                196.6999969482422,
                10974.818359375
            ],
            "ypr": [
                -45.836585998535159,
                0.0,
                0.0
            ],
            "scale": 1.0,
            "enableCEPersistency": 0
        },
        {
            "name": "WoodenLog",
            "pos": [
                10790.619140625,
                196.6999969482422,
                10974.666015625
            ],
            "ypr": [
                -45.836585998535159,
                0.0,
                0.0
            ],
            "scale": 1.0,
            "enableCEPersistency": 0
        },
        {
            "name": "WoodenLog",
            "pos": [
                10790.3701171875,
                196.6999969482422,
                10974.37890625
            ],
            "ypr": [
                -45.836585998535159,
                0.0,
                0.0
            ],
            "scale": 1.0,
            "enableCEPersistency": 0
        },
        {
            "name": "WoodenLog",
            "pos": [
                10790.4990234375,
                196.6999969482422,
                10974.53125
            ],
            "ypr": [
                -45.836585998535159,
                0.0,
                0.0
            ],
            "scale": 1.0,
            "enableCEPersistency": 0
        },
        {
            "name": "WoodenLog",
            "pos": [
                10791.0,
                196.6999969482422,
                10975.099609375
            ],
            "ypr": [
                -45.836585998535159,
                0.0,
                0.0
            ],
            "scale": 1.0,
            "enableCEPersistency": 0
        },
        {
            "name": "WoodenLog",
            "pos": [
                10790.87109375,
                196.6999969482422,
                10974.947265625
            ],
            "ypr": [
                -45.836585998535159,
                0.0,
                0.0
            ],
            "scale": 1.0,
            "enableCEPersistency": 0
        },
        {
            "name": "WoodenLog",
            "pos": [
                10790.748046875,
                196.6999969482422,
                10974.818359375
            ],
            "ypr": [
                -45.836585998535159,
                0.0,
                0.0
            ],
            "scale": 1.0,
            "enableCEPersistency": 0
        },
        {
            "name": "WoodenLog",
            "pos": [
                10790.619140625,
                196.6999969482422,
                10974.666015625
            ],
            "ypr": [
                -45.836585998535159,
                0.0,
                0.0
            ],
            "scale": 1.0,
            "enableCEPersistency": 0
        },
        {
            "name": "WoodenLog",
            "pos": [
                10790.3701171875,
                196.6999969482422,
                10974.37890625
            ],
            "ypr": [
                -45.836585998535159,
                0.0,
                0.0
            ],
            "scale": 1.0,
            "enableCEPersistency": 0
        },
        {
            "name": "WoodenLog",
            "pos": [
                10790.4990234375,
                196.6999969482422,
                10974.53125
            ],
            "ypr": [
                -45.836585998535159,
                0.0,
                0.0
            ],
            "scale": 1.0,
            "enableCEPersistency": 0
        },
        {
            "name": "WoodenLog",
            "pos": [
                10791.0,
                196.6999969482422,
                10975.099609375
            ],
            "ypr": [
                -45.836585998535159,
                0.0,
                0.0
            ],
            "scale": 1.0,
            "enableCEPersistency": 0
        },
        {
            "name": "WoodenLog",
            "pos": [
                10790.87109375,
                196.6999969482422,
                10974.947265625
            ],
            "ypr": [
                -45.836585998535159,
                0.0,
                0.0
            ],
            "scale": 1.0,
            "enableCEPersistency": 0
        },
        {
            "name": "WoodenLog",
            "pos": [
                10790.748046875,
                196.6999969482422,
                10974.818359375
            ],
            "ypr": [
                -45.836585998535159,
                0.0,
                0.0
            ],
            "scale": 1.0,
            "enableCEPersistency": 0
        },
        {
            "name": "WoodenLog",
            "pos": [
                10790.619140625,
                196.6999969482422,
                10974.666015625
            ],
            "ypr": [
                -45.836585998535159,
                0.0,
                0.0
            ],
            "scale": 1.0,
            "enableCEPersistency": 0
        },
        {
            "name": "WoodenLog",
            "pos": [
                10790.3701171875,
                196.6999969482422,
                10974.37890625
            ],
            "ypr": [
                -45.836585998535159,
                0.0,
                0.0
            ],
            "scale": 1.0,
            "enableCEPersistency": 0
        },
        {
            "name": "WoodenLog",
            "pos": [
                10790.4990234375,
                196.6999969482422,
                10974.53125
            ],
            "ypr": [
                -45.836585998535159,
                0.0,
                0.0
            ],
            "scale": 1.0,
            "enableCEPersistency": 0
        },
        {
            "name": "WoodenLog",
            "pos": [
                10791.0,
                196.6999969482422,
                10975.099609375
            ],
            "ypr": [
                -45.836585998535159,
                0.0,
                0.0
            ],
            "scale": 1.0,
            "enableCEPersistency": 0
        },
        {
            "name": "WoodenLog",
            "pos": [
                10790.87109375,
                196.6999969482422,
                10974.947265625
            ],
            "ypr": [
                -45.836585998535159,
                0.0,
                0.0
            ],
            "scale": 1.0,
            "enableCEPersistency": 0
        },
        {
            "name": "WoodenLog",
            "pos": [
                10790.748046875,
                196.6999969482422,
                10974.818359375
            ],
            "ypr": [
                -45.836585998535159,
                0.0,
                0.0
            ],
            "scale": 1.0,
            "enableCEPersistency": 0
        },
        {
            "name": "WoodenLog",
            "pos": [
                10790.619140625,
                196.6999969482422,
                10974.666015625
            ],
            "ypr": [
                -45.836585998535159,
                0.0,
                0.0
            ],
            "scale": 1.0,
            "enableCEPersistency": 0
        },
        {
            "name": "WoodenLog",
            "pos": [
                10790.3701171875,
                196.6999969482422,
                10974.37890625
            ],
            "ypr": [
                -45.836585998535159,
                0.0,
                0.0
            ],
            "scale": 1.0,
            "enableCEPersistency": 0
        },
        {
            "name": "WoodenLog",
            "pos": [
                10790.4990234375,
                196.6999969482422,
                10974.53125
            ],
            "ypr": [
                -45.836585998535159,
                0.0,
                0.0
            ],
            "scale": 1.0,
            "enableCEPersistency": 0
        },
        {
            "name": "WoodenLog",
            "pos": [
                10791.0,
                196.6999969482422,
                10975.099609375
            ],
            "ypr": [
                -45.836585998535159,
                0.0,
                0.0
            ],
            "scale": 1.0,
            "enableCEPersistency": 0
        },
        {
            "name": "WoodenLog",
            "pos": [
                10790.87109375,
                196.6999969482422,
                10974.947265625
            ],
            "ypr": [
                -45.836585998535159,
                0.0,
                0.0
            ],
            "scale": 1.0,
            "enableCEPersistency": 0
        },
        {
            "name": "WoodenLog",
            "pos": [
                10790.748046875,
                196.6999969482422,
                10974.818359375
            ],
            "ypr": [
                -45.836585998535159,
                0.0,
                0.0
            ],
            "scale": 1.0,
            "enableCEPersistency": 0
        },
        {
            "name": "WoodenLog",
            "pos": [
                10790.619140625,
                196.6999969482422,
                10974.666015625
            ],
            "ypr": [
                -45.836585998535159,
                0.0,
                0.0
            ],
            "scale": 1.0,
            "enableCEPersistency": 0
        },
        {
            "name": "WoodenLog",
            "pos": [
                10790.3701171875,
                196.6999969482422,
                10974.37890625
            ],
            "ypr": [
                -45.836585998535159,
                0.0,
                0.0
            ],
            "scale": 1.0,
            "enableCEPersistency": 0
        },
        {
            "name": "WoodenLog",
            "pos": [
                10790.4990234375,
                196.6999969482422,
                10974.53125
            ],
            "ypr": [
                -45.836585998535159,
                0.0,
                0.0
            ],
            "scale": 1.0,
            "enableCEPersistency": 0
        },
        {
            "name": "WoodenLog",
            "pos": [
                10791.0,
                196.6999969482422,
                10975.099609375
            ],
            "ypr": [
                -45.836585998535159,
                0.0,
                0.0
            ],
            "scale": 1.0,
            "enableCEPersistency": 0
        },
        {
            "name": "WoodenLog",
            "pos": [
                10790.87109375,
                196.6999969482422,
                10974.947265625
            ],
            "ypr": [
                -45.836585998535159,
                0.0,
                0.0
            ],
            "scale": 1.0,
            "enableCEPersistency": 0
        },
        {
            "name": "WoodenLog",
            "pos": [
                10790.748046875,
                196.6999969482422,
                10974.818359375
            ],
            "ypr": [
                -45.836585998535159,
                0.0,
                0.0
            ],
            "scale": 1.0,
            "enableCEPersistency": 0
        },
        {
            "name": "WoodenLog",
            "pos": [
                10790.619140625,
                196.6999969482422,
                10974.666015625
            ],
            "ypr": [
                -45.836585998535159,
                0.0,
                0.0
            ],
            "scale": 1.0,
            "enableCEPersistency": 0
        },
        {
            "name": "WoodenLog",
            "pos": [
                10790.3701171875,
                196.6999969482422,
                10974.37890625
            ],
            "ypr": [
                -45.836585998535159,
                0.0,
                0.0
            ],
            "scale": 1.0,
            "enableCEPersistency": 0
        },
        {
            "name": "WoodenLog",
            "pos": [
                10790.4990234375,
                196.6999969482422,
                10974.53125
            ],
            "ypr": [
                -45.836585998535159,
                0.0,
                0.0
            ],
            "scale": 1.0,
            "enableCEPersistency": 0
        },
        {
            "name": "MetalPlate",
            "pos": [
                10791.5,
                196.6999969482422,
                10975.7998046875
            ],
            "ypr": [
                44.833900451660159,
                0.0,
                0.0
            ],
            "scale": 1.0,
            "enableCEPersistency": 0
        },
        {
            "name": "MetalPlate",
            "pos": [
                10791.5,
                196.6999969482422,
                10975.7998046875
            ],
            "ypr": [
                44.833900451660159,
                0.0,
                0.0
            ],
            "scale": 1.0,
            "enableCEPersistency": 0
        },
        {
            "name": "MetalPlate",
            "pos": [
                10791.5,
                196.6999969482422,
                10975.7998046875
            ],
            "ypr": [
                44.833900451660159,
                0.0,
                0.0
            ],
            "scale": 1.0,
            "enableCEPersistency": 0
        },
        {
            "name": "MetalPlate",
            "pos": [
                10791.5,
                196.6999969482422,
                10975.7998046875
            ],
            "ypr": [
                44.833900451660159,
                0.0,
                0.0
            ],
            "scale": 1.0,
            "enableCEPersistency": 0
        },
        {
            "name": "MetalPlate",
            "pos": [
                10791.5,
                196.6999969482422,
                10975.7998046875
            ],
            "ypr": [
                44.833900451660159,
                0.0,
                0.0
            ],
            "scale": 1.0,
            "enableCEPersistency": 0
        },
        {
            "name": "MetalPlate",
            "pos": [
                10791.5,
                196.6999969482422,
                10975.7998046875
            ],
            "ypr": [
                44.833900451660159,
                0.0,
                0.0
            ],
            "scale": 1.0,
            "enableCEPersistency": 0
        },
        {
            "name": "MetalPlate",
            "pos": [
                10791.5,
                196.6999969482422,
                10975.7998046875
            ],
            "ypr": [
                44.833900451660159,
                0.0,
                0.0
            ],
            "scale": 1.0,
            "enableCEPersistency": 0
        },
        {
            "name": "MetalPlate",
            "pos": [
                10791.5,
                196.6999969482422,
                10975.7998046875
            ],
            "ypr": [
                44.833900451660159,
                0.0,
                0.0
            ],
            "scale": 1.0,
            "enableCEPersistency": 0
        },
        {
            "name": "MetalPlate",
            "pos": [
                10791.5,
                196.6999969482422,
                10975.7998046875
            ],
            "ypr": [
                44.833900451660159,
                0.0,
                0.0
            ],
            "scale": 1.0,
            "enableCEPersistency": 0
        },
        {
            "name": "MetalPlate",
            "pos": [
                10791.5,
                196.6999969482422,
                10975.7998046875
            ],
            "ypr": [
                44.833900451660159,
                0.0,
                0.0
            ],
            "scale": 1.0,
            "enableCEPersistency": 0
        },
        {
            "name": "MetalPlate",
            "pos": [
                10791.5,
                196.6999969482422,
                10975.7998046875
            ],
            "ypr": [
                44.833900451660159,
                0.0,
                0.0
            ],
            "scale": 1.0,
            "enableCEPersistency": 0
        },
        {
            "name": "MetalPlate",
            "pos": [
                10791.5,
                196.6999969482422,
                10975.7998046875
            ],
            "ypr": [
                44.833900451660159,
                0.0,
                0.0
            ],
            "scale": 1.0,
            "enableCEPersistency": 0
        },
        {
            "name": "MetalPlate",
            "pos": [
                10791.5,
                196.6999969482422,
                10975.7998046875
            ],
            "ypr": [
                44.833900451660159,
                0.0,
                0.0
            ],
            "scale": 1.0,
            "enableCEPersistency": 0
        },
        {
            "name": "MetalPlate",
            "pos": [
                10791.5,
                196.6999969482422,
                10975.7998046875
            ],
            "ypr": [
                44.833900451660159,
                0.0,
                0.0
            ],
            "scale": 1.0,
            "enableCEPersistency": 0
        },
        {
            "name": "MetalPlate",
            "pos": [
                10791.5,
                196.6999969482422,
                10975.7998046875
            ],
            "ypr": [
                44.833900451660159,
                0.0,
                0.0
            ],
            "scale": 1.0,
            "enableCEPersistency": 0
        },
        {
            "name": "MetalPlate",
            "pos": [
                10791.5,
                196.6999969482422,
                10975.7998046875
            ],
            "ypr": [
                44.833900451660159,
                0.0,
                0.0
            ],
            "scale": 1.0,
            "enableCEPersistency": 0
        },
        {
            "name": "MetalPlate",
            "pos": [
                10791.5,
                196.6999969482422,
                10975.7998046875
            ],
            "ypr": [
                44.833900451660159,
                0.0,
                0.0
            ],
            "scale": 1.0,
            "enableCEPersistency": 0
        },
        {
            "name": "MetalPlate",
            "pos": [
                10791.5,
                196.6999969482422,
                10975.7998046875
            ],
            "ypr": [
                44.833900451660159,
                0.0,
                0.0
            ],
            "scale": 1.0,
            "enableCEPersistency": 0
        },
        {
            "name": "MetalPlate",
            "pos": [
                10791.5,
                196.6999969482422,
                10975.7998046875
            ],
            "ypr": [
                44.833900451660159,
                0.0,
                0.0
            ],
            "scale": 1.0,
            "enableCEPersistency": 0
        },
        {
            "name": "MetalPlate",
            "pos": [
                10791.5,
                196.6999969482422,
                10975.7998046875
            ],
            "ypr": [
                44.833900451660159,
                0.0,
                0.0
            ],
            "scale": 1.0,
            "enableCEPersistency": 0
        },
        {
            "name": "MetalPlate",
            "pos": [
                10791.5,
                196.6999969482422,
                10975.7998046875
            ],
            "ypr": [
                44.833900451660159,
                0.0,
                0.0
            ],
            "scale": 1.0,
            "enableCEPersistency": 0
        },
        {
            "name": "MetalPlate",
            "pos": [
                10791.5,
                196.6999969482422,
                10975.7998046875
            ],
            "ypr": [
                44.833900451660159,
                0.0,
                0.0
            ],
            "scale": 1.0,
            "enableCEPersistency": 0
        },
        {
            "name": "MetalPlate",
            "pos": [
                10791.5,
                196.6999969482422,
                10975.7998046875
            ],
            "ypr": [
                44.833900451660159,
                0.0,
                0.0
            ],
            "scale": 1.0,
            "enableCEPersistency": 0
        },
        {
            "name": "MetalPlate",
            "pos": [
                10791.5,
                196.6999969482422,
                10975.7998046875
            ],
            "ypr": [
                44.833900451660159,
                0.0,
                0.0
            ],
            "scale": 1.0,
            "enableCEPersistency": 0
        },
        {
            "name": "MetalPlate",
            "pos": [
                10791.5,
                196.6999969482422,
                10975.7998046875
            ],
            "ypr": [
                44.833900451660159,
                0.0,
                0.0
            ],
            "scale": 1.0,
            "enableCEPersistency": 0
        },
        {
            "name": "MetalPlate",
            "pos": [
                10791.5,
                196.6999969482422,
                10975.7998046875
            ],
            "ypr": [
                44.833900451660159,
                0.0,
                0.0
            ],
            "scale": 1.0,
            "enableCEPersistency": 0
        },
        {
            "name": "MetalPlate",
            "pos": [
                10791.5,
                196.6999969482422,
                10975.7998046875
            ],
            "ypr": [
                44.833900451660159,
                0.0,
                0.0
            ],
            "scale": 1.0,
            "enableCEPersistency": 0
        },
        {
            "name": "MetalPlate",
            "pos": [
                10791.5,
                196.6999969482422,
                10975.7998046875
            ],
            "ypr": [
                44.833900451660159,
                0.0,
                0.0
            ],
            "scale": 1.0,
            "enableCEPersistency": 0
        },
        {
            "name": "MetalPlate",
            "pos": [
                10791.5,
                196.6999969482422,
                10975.7998046875
            ],
            "ypr": [
                44.833900451660159,
                0.0,
                0.0
            ],
            "scale": 1.0,
            "enableCEPersistency": 0
        },
        {
            "name": "MetalPlate",
            "pos": [
                10791.5,
                196.6999969482422,
                10975.7998046875
            ],
            "ypr": [
                44.833900451660159,
                0.0,
                0.0
            ],
            "scale": 1.0,
            "enableCEPersistency": 0
        },
        {
            "name": "MetalPlate",
            "pos": [
                10791.5,
                196.6999969482422,
                10975.7998046875
            ],
            "ypr": [
                44.833900451660159,
                0.0,
                0.0
            ],
            "scale": 1.0,
            "enableCEPersistency": 0
        },
        {
            "name": "MetalPlate",
            "pos": [
                10791.5,
                196.6999969482422,
                10975.7998046875
            ],
            "ypr": [
                44.833900451660159,
                0.0,
                0.0
            ],
            "scale": 1.0,
            "enableCEPersistency": 0
        },
        {
            "name": "MetalPlate",
            "pos": [
                10791.5,
                196.6999969482422,
                10975.7998046875
            ],
            "ypr": [
                44.833900451660159,
                0.0,
                0.0
            ],
            "scale": 1.0,
            "enableCEPersistency": 0
        },
        {
            "name": "MetalPlate",
            "pos": [
                10791.5,
                196.6999969482422,
                10975.7998046875
            ],
            "ypr": [
                44.833900451660159,
                0.0,
                0.0
            ],
            "scale": 1.0,
            "enableCEPersistency": 0
        },
        {
            "name": "MetalPlate",
            "pos": [
                10791.5,
                196.6999969482422,
                10975.7998046875
            ],
            "ypr": [
                44.833900451660159,
                0.0,
                0.0
            ],
            "scale": 1.0,
            "enableCEPersistency": 0
        },
        {
            "name": "MetalPlate",
            "pos": [
                10791.5,
                196.6999969482422,
                10975.7998046875
            ],
            "ypr": [
                44.833900451660159,
                0.0,
                0.0
            ],
            "scale": 1.0,
            "enableCEPersistency": 0
        },
        {
            "name": "MetalPlate",
            "pos": [
                10791.5,
                196.6999969482422,
                10975.7998046875
            ],
            "ypr": [
                44.833900451660159,
                0.0,
                0.0
            ],
            "scale": 1.0,
            "enableCEPersistency": 0
        },
        {
            "name": "MetalPlate",
            "pos": [
                10791.5,
                196.6999969482422,
                10975.7998046875
            ],
            "ypr": [
                44.833900451660159,
                0.0,
                0.0
            ],
            "scale": 1.0,
            "enableCEPersistency": 0
        },
        {
            "name": "MetalPlate",
            "pos": [
                10791.5,
                196.6999969482422,
                10975.7998046875
            ],
            "ypr": [
                44.833900451660159,
                0.0,
                0.0
            ],
            "scale": 1.0,
            "enableCEPersistency": 0
        },
        {
            "name": "MetalPlate",
            "pos": [
                10791.5,
                196.6999969482422,
                10975.7998046875
            ],
            "ypr": [
                44.833900451660159,
                0.0,
                0.0
            ],
            "scale": 1.0,
            "enableCEPersistency": 0
        },
        {
            "name": "MetalPlate",
            "pos": [
                10791.5,
                196.6999969482422,
                10975.7998046875
            ],
            "ypr": [
                44.833900451660159,
                0.0,
                0.0
            ],
            "scale": 1.0,
            "enableCEPersistency": 0
        },
        {
            "name": "MetalPlate",
            "pos": [
                10791.5,
                196.6999969482422,
                10975.7998046875
            ],
            "ypr": [
                44.833900451660159,
                0.0,
                0.0
            ],
            "scale": 1.0,
            "enableCEPersistency": 0
        },
        {
            "name": "MetalPlate",
            "pos": [
                10791.5,
                196.6999969482422,
                10975.7998046875
            ],
            "ypr": [
                44.833900451660159,
                0.0,
                0.0
            ],
            "scale": 1.0,
            "enableCEPersistency": 0
        },
        {
            "name": "MetalPlate",
            "pos": [
                10791.5,
                196.6999969482422,
                10975.7998046875
            ],
            "ypr": [
                44.833900451660159,
                0.0,
                0.0
            ],
            "scale": 1.0,
            "enableCEPersistency": 0
        },
        {
            "name": "MetalPlate",
            "pos": [
                10791.5,
                196.6999969482422,
                10975.7998046875
            ],
            "ypr": [
                44.833900451660159,
                0.0,
                0.0
            ],
            "scale": 1.0,
            "enableCEPersistency": 0
        },
        {
            "name": "MetalPlate",
            "pos": [
                10791.5,
                196.6999969482422,
                10975.7998046875
            ],
            "ypr": [
                44.833900451660159,
                0.0,
                0.0
            ],
            "scale": 1.0,
            "enableCEPersistency": 0
        },
        {
            "name": "MetalPlate",
            "pos": [
                10791.5,
                196.6999969482422,
                10975.7998046875
            ],
            "ypr": [
                44.833900451660159,
                0.0,
                0.0
            ],
            "scale": 1.0,
            "enableCEPersistency": 0
        },
        {
            "name": "MetalPlate",
            "pos": [
                10791.5,
                196.6999969482422,
                10975.7998046875
            ],
            "ypr": [
                44.833900451660159,
                0.0,
                0.0
            ],
            "scale": 1.0,
            "enableCEPersistency": 0
        },
        {
            "name": "HandSaw",
            "pos": [
                10796.6005859375,
                197.5500030517578,
                10980.7392578125
            ],
            "ypr": [
                45.0,
                0.0,
                90.0
            ],
            "scale": 0.9999974966049194,
            "enableCEPersistency": 0
        },
        {
            "name": "HandSaw",
            "pos": [
                10796.5126953125,
                197.5500030517578,
                10980.8271484375
            ],
            "ypr": [
                45.0,
                0.0,
                90.0
            ],
            "scale": 0.9999974966049194,
            "enableCEPersistency": 0
        },
        {
            "name": "HandSaw",
            "pos": [
                10796.4306640625,
                197.5500030517578,
                10980.9150390625
            ],
            "ypr": [
                45.0,
                0.0,
                90.0
            ],
            "scale": 0.9999974966049194,
            "enableCEPersistency": 0
        },
        {
            "name": "HandSaw",
            "pos": [
                10796.345703125,
                197.5500030517578,
                10981.0
            ],
            "ypr": [
                45.0,
                0.0,
                90.0
            ],
            "scale": 0.9999974966049194,
            "enableCEPersistency": 0
        },
        {
            "name": "HandSaw",
            "pos": [
                10796.26953125,
                197.5500030517578,
                10981.08203125
            ],
            "ypr": [
                45.0,
                0.0,
                90.0
            ],
            "scale": 0.9999974966049194,
            "enableCEPersistency": 0
        },
        {
            "name": "HandSaw",
            "pos": [
                10796.1787109375,
                197.5500030517578,
                10981.1787109375
            ],
            "ypr": [
                45.0,
                0.0,
                90.0
            ],
            "scale": 0.9999974966049194,
            "enableCEPersistency": 0
        },
        {
            "name": "PileOfWoodenPlanks",
            "pos": [
                10793.2998046875,
                197.9600067138672,
                10978.0
            ],
            "ypr": [
                -47.12559509277344,
                0.0,
                0.0
            ],
            "scale": 0.9999999403953552,
            "enableCEPersistency": 0
        },
        {
            "name": "WoodenLog",
            "pos": [
                10790.87109375,
                196.6999969482422,
                10974.947265625
            ],
            "ypr": [
                -45.836585998535159,
                0.0,
                0.0
            ],
            "scale": 1.0,
            "enableCEPersistency": 0
        },
        {
            "name": "WoodenLog",
            "pos": [
                10790.748046875,
                196.6999969482422,
                10974.818359375
            ],
            "ypr": [
                -45.836585998535159,
                0.0,
                0.0
            ],
            "scale": 1.0,
            "enableCEPersistency": 0
        },
        {
            "name": "WoodenLog",
            "pos": [
                10790.619140625,
                196.6999969482422,
                10974.666015625
            ],
            "ypr": [
                -45.836585998535159,
                0.0,
                0.0
            ],
            "scale": 1.0,
            "enableCEPersistency": 0
        },
        {
            "name": "WoodenLog",
            "pos": [
                10790.3701171875,
                196.6999969482422,
                10974.37890625
            ],
            "ypr": [
                -45.836585998535159,
                0.0,
                0.0
            ],
            "scale": 1.0,
            "enableCEPersistency": 0
        },
        {
            "name": "WoodenLog",
            "pos": [
                10790.4990234375,
                196.6999969482422,
                10974.53125
            ],
            "ypr": [
                -45.836585998535159,
                0.0,
                0.0
            ],
            "scale": 1.0,
            "enableCEPersistency": 0
        },
        {
            "name": "WoodenLog",
            "pos": [
                10791.0,
                196.6999969482422,
                10975.099609375
            ],
            "ypr": [
                -45.836585998535159,
                0.0,
                0.0
            ],
            "scale": 1.0,
            "enableCEPersistency": 0
        },
        {
            "name": "WoodenLog",
            "pos": [
                10790.87109375,
                196.6999969482422,
                10974.947265625
            ],
            "ypr": [
                -45.836585998535159,
                0.0,
                0.0
            ],
            "scale": 1.0,
            "enableCEPersistency": 0
        },
        {
            "name": "WoodenLog",
            "pos": [
                10790.748046875,
                196.6999969482422,
                10974.818359375
            ],
            "ypr": [
                -45.836585998535159,
                0.0,
                0.0
            ],
            "scale": 1.0,
            "enableCEPersistency": 0
        },
        {
            "name": "WoodenLog",
            "pos": [
                10790.619140625,
                196.6999969482422,
                10974.666015625
            ],
            "ypr": [
                -45.836585998535159,
                0.0,
                0.0
            ],
            "scale": 1.0,
            "enableCEPersistency": 0
        },
        {
            "name": "WoodenLog",
            "pos": [
                10790.3701171875,
                196.6999969482422,
                10974.37890625
            ],
            "ypr": [
                -45.836585998535159,
                0.0,
                0.0
            ],
            "scale": 1.0,
            "enableCEPersistency": 0
        },
        {
            "name": "WoodenLog",
            "pos": [
                10790.4990234375,
                196.6999969482422,
                10974.53125
            ],
            "ypr": [
                -45.836585998535159,
                0.0,
                0.0
            ],
            "scale": 1.0,
            "enableCEPersistency": 0
        },
        {
            "name": "WoodenLog",
            "pos": [
                10791.0,
                196.6999969482422,
                10975.099609375
            ],
            "ypr": [
                -45.836585998535159,
                0.0,
                0.0
            ],
            "scale": 1.0,
            "enableCEPersistency": 0
        },
        {
            "name": "WoodenLog",
            "pos": [
                10790.87109375,
                196.6999969482422,
                10974.947265625
            ],
            "ypr": [
                -45.836585998535159,
                0.0,
                0.0
            ],
            "scale": 1.0,
            "enableCEPersistency": 0
        },
        {
            "name": "WoodenLog",
            "pos": [
                10790.748046875,
                196.6999969482422,
                10974.818359375
            ],
            "ypr": [
                -45.836585998535159,
                0.0,
                0.0
            ],
            "scale": 1.0,
            "enableCEPersistency": 0
        },
        {
            "name": "WoodenLog",
            "pos": [
                10790.619140625,
                196.6999969482422,
                10974.666015625
            ],
            "ypr": [
                -45.836585998535159,
                0.0,
                0.0
            ],
            "scale": 1.0,
            "enableCEPersistency": 0
        },
        {
            "name": "WoodenLog",
            "pos": [
                10790.3701171875,
                196.6999969482422,
                10974.37890625
            ],
            "ypr": [
                -45.836585998535159,
                0.0,
                0.0
            ],
            "scale": 1.0,
            "enableCEPersistency": 0
        },
        {
            "name": "WoodenLog",
            "pos": [
                10790.4990234375,
                196.6999969482422,
                10974.53125
            ],
            "ypr": [
                -45.836585998535159,
                0.0,
                0.0
            ],
            "scale": 1.0,
            "enableCEPersistency": 0
        },
        {
            "name": "WoodenLog",
            "pos": [
                10791.0,
                196.6999969482422,
                10975.099609375
            ],
            "ypr": [
                -45.836585998535159,
                0.0,
                0.0
            ],
            "scale": 1.0,
            "enableCEPersistency": 0
        },
        {
            "name": "WoodenLog",
            "pos": [
                10790.87109375,
                196.6999969482422,
                10974.947265625
            ],
            "ypr": [
                -45.836585998535159,
                0.0,
                0.0
            ],
            "scale": 1.0,
            "enableCEPersistency": 0
        },
        {
            "name": "WoodenLog",
            "pos": [
                10790.748046875,
                196.6999969482422,
                10974.818359375
            ],
            "ypr": [
                -45.836585998535159,
                0.0,
                0.0
            ],
            "scale": 1.0,
            "enableCEPersistency": 0
        },
        {
            "name": "WoodenLog",
            "pos": [
                10790.619140625,
                196.6999969482422,
                10974.666015625
            ],
            "ypr": [
                -45.836585998535159,
                0.0,
                0.0
            ],
            "scale": 1.0,
            "enableCEPersistency": 0
        },
        {
            "name": "WoodenLog",
            "pos": [
                10790.3701171875,
                196.6999969482422,
                10974.37890625
            ],
            "ypr": [
                -45.836585998535159,
                0.0,
                0.0
            ],
            "scale": 1.0,
            "enableCEPersistency": 0
        },
        {
            "name": "WoodenLog",
            "pos": [
                10790.4990234375,
                196.6999969482422,
                10974.53125
            ],
            "ypr": [
                -45.836585998535159,
                0.0,
                0.0
            ],
            "scale": 1.0,
            "enableCEPersistency": 0
        },
        {
            "name": "WoodenLog",
            "pos": [
                10791.0,
                196.6999969482422,
                10975.099609375
            ],
            "ypr": [
                -45.836585998535159,
                0.0,
                0.0
            ],
            "scale": 1.0,
            "enableCEPersistency": 0
        },
        {
            "name": "WoodenLog",
            "pos": [
                10790.87109375,
                196.6999969482422,
                10974.947265625
            ],
            "ypr": [
                -45.836585998535159,
                0.0,
                0.0
            ],
            "scale": 1.0,
            "enableCEPersistency": 0
        },
        {
            "name": "WoodenLog",
            "pos": [
                10790.748046875,
                196.6999969482422,
                10974.818359375
            ],
            "ypr": [
                -45.836585998535159,
                0.0,
                0.0
            ],
            "scale": 1.0,
            "enableCEPersistency": 0
        },
        {
            "name": "WoodenLog",
            "pos": [
                10790.619140625,
                196.6999969482422,
                10974.666015625
            ],
            "ypr": [
                -45.836585998535159,
                0.0,
                0.0
            ],
            "scale": 1.0,
            "enableCEPersistency": 0
        },
        {
            "name": "WoodenLog",
            "pos": [
                10790.3701171875,
                196.6999969482422,
                10974.37890625
            ],
            "ypr": [
                -45.836585998535159,
                0.0,
                0.0
            ],
            "scale": 1.0,
            "enableCEPersistency": 0
        },
        {
            "name": "WoodenLog",
            "pos": [
                10790.4990234375,
                196.6999969482422,
                10974.53125
            ],
            "ypr": [
                -45.836585998535159,
                0.0,
                0.0
            ],
            "scale": 1.0,
            "enableCEPersistency": 0
        },
        {
            "name": "WoodenLog",
            "pos": [
                10791.0,
                196.6999969482422,
                10975.099609375
            ],
            "ypr": [
                -45.836585998535159,
                0.0,
                0.0
            ],
            "scale": 1.0,
            "enableCEPersistency": 0
        },
        {
            "name": "WoodenLog",
            "pos": [
                10790.87109375,
                196.6999969482422,
                10974.947265625
            ],
            "ypr": [
                -45.836585998535159,
                0.0,
                0.0
            ],
            "scale": 1.0,
            "enableCEPersistency": 0
        },
        {
            "name": "WoodenLog",
            "pos": [
                10790.748046875,
                196.6999969482422,
                10974.818359375
            ],
            "ypr": [
                -45.836585998535159,
                0.0,
                0.0
            ],
            "scale": 1.0,
            "enableCEPersistency": 0
        },
        {
            "name": "WoodenLog",
            "pos": [
                10790.619140625,
                196.6999969482422,
                10974.666015625
            ],
            "ypr": [
                -45.836585998535159,
                0.0,
                0.0
            ],
            "scale": 1.0,
            "enableCEPersistency": 0
        },
        {
            "name": "WoodenLog",
            "pos": [
                10790.3701171875,
                196.6999969482422,
                10974.37890625
            ],
            "ypr": [
                -45.836585998535159,
                0.0,
                0.0
            ],
            "scale": 1.0,
            "enableCEPersistency": 0
        },
        {
            "name": "WoodenLog",
            "pos": [
                10790.4990234375,
                196.6999969482422,
                10974.53125
            ],
            "ypr": [
                -45.836585998535159,
                0.0,
                0.0
            ],
            "scale": 1.0,
            "enableCEPersistency": 0
        },
        {
            "name": "WoodenLog",
            "pos": [
                10791.0,
                196.6999969482422,
                10975.099609375
            ],
            "ypr": [
                -45.836585998535159,
                0.0,
                0.0
            ],
            "scale": 1.0,
            "enableCEPersistency": 0
        },
        {
            "name": "WoodenLog",
            "pos": [
                10790.87109375,
                196.6999969482422,
                10974.947265625
            ],
            "ypr": [
                -45.836585998535159,
                0.0,
                0.0
            ],
            "scale": 1.0,
            "enableCEPersistency": 0
        },
        {
            "name": "WoodenLog",
            "pos": [
                10790.748046875,
                196.6999969482422,
                10974.818359375
            ],
            "ypr": [
                -45.836585998535159,
                0.0,
                0.0
            ],
            "scale": 1.0,
            "enableCEPersistency": 0
        },
        {
            "name": "WoodenLog",
            "pos": [
                10790.619140625,
                196.6999969482422,
                10974.666015625
            ],
            "ypr": [
                -45.836585998535159,
                0.0,
                0.0
            ],
            "scale": 1.0,
            "enableCEPersistency": 0
        },
        {
            "name": "WoodenLog",
            "pos": [
                10790.3701171875,
                196.6999969482422,
                10974.37890625
            ],
            "ypr": [
                -45.836585998535159,
                0.0,
                0.0
            ],
            "scale": 1.0,
            "enableCEPersistency": 0
        },
        {
            "name": "WoodenLog",
            "pos": [
                10790.4990234375,
                196.6999969482422,
                10974.53125
            ],
            "ypr": [
                -45.836585998535159,
                0.0,
                0.0
            ],
            "scale": 1.0,
            "enableCEPersistency": 0
        },
        {
            "name": "WoodenLog",
            "pos": [
                10791.0,
                196.6999969482422,
                10975.099609375
            ],
            "ypr": [
                -45.836585998535159,
                0.0,
                0.0
            ],
            "scale": 1.0,
            "enableCEPersistency": 0
        },
        {
            "name": "WoodenLog",
            "pos": [
                10790.87109375,
                196.6999969482422,
                10974.947265625
            ],
            "ypr": [
                -45.836585998535159,
                0.0,
                0.0
            ],
            "scale": 1.0,
            "enableCEPersistency": 0
        },
        {
            "name": "WoodenLog",
            "pos": [
                10790.748046875,
                196.6999969482422,
                10974.818359375
            ],
            "ypr": [
                -45.836585998535159,
                0.0,
                0.0
            ],
            "scale": 1.0,
            "enableCEPersistency": 0
        },
        {
            "name": "WoodenLog",
            "pos": [
                10790.619140625,
                196.6999969482422,
                10974.666015625
            ],
            "ypr": [
                -45.836585998535159,
                0.0,
                0.0
            ],
            "scale": 1.0,
            "enableCEPersistency": 0
        },
        {
            "name": "WoodenLog",
            "pos": [
                10790.3701171875,
                196.6999969482422,
                10974.37890625
            ],
            "ypr": [
                -45.836585998535159,
                0.0,
                0.0
            ],
            "scale": 1.0,
            "enableCEPersistency": 0
        },
        {
            "name": "WoodenLog",
            "pos": [
                10790.4990234375,
                196.6999969482422,
                10974.53125
            ],
            "ypr": [
                -45.836585998535159,
                0.0,
                0.0
            ],
            "scale": 1.0,
            "enableCEPersistency": 0
        },
        {
            "name": "WoodenLog",
            "pos": [
                10791.0,
                196.6999969482422,
                10975.099609375
            ],
            "ypr": [
                -45.836585998535159,
                0.0,
                0.0
            ],
            "scale": 1.0,
            "enableCEPersistency": 0
        }
    ]
}